[
  {
    "Type": "KeyUp",
    "Time": 103,
    "X": null,
    "Y": null,
    "Delta": null,
    "KeyCode": 35
  },
  {
    "Type": "MouseMove",
    "Time": 147,
    "X": 756,
    "Y": 615,
    "Delta": null,
    "KeyCode": null
  },
  {
    "Type": "MouseMove",
    "Time": 177,
    "X": 756,
    "Y": 612,
    "Delta": null,
    "KeyCode": null
  },
  {
    "Type": "MouseMove",
    "Time": 261,
    "X": 756,
    "Y": 609,
    "Delta": null,
    "KeyCode": null
  },
  {
    "Type": "MouseMove",
    "Time": 283,
    "X": 750,
    "Y": 594,
    "Delta": null,
    "KeyCode": null
  },
  {
    "Type": "MouseMove",
    "Time": 287,
    "X": 747,
    "Y": 588,
    "Delta": null,
    "KeyCode": null
  },
  {
    "Type": "MouseMove",
    "Time": 295,
    "X": 741,
    "Y": 585,
    "Delta": null,
    "KeyCode": null
  },
  {
    "Type": "MouseMove",
    "Time": 316,
    "X": 732,
    "Y": 573,
    "Delta": null,
    "KeyCode": null
  },
  {
    "Type": "MouseMove",
    "Time": 319,
    "X": 726,
    "Y": 561,
    "Delta": null,
    "KeyCode": null
  },
  {
    "Type": "MouseMove",
    "Time": 327,
    "X": 720,
    "Y": 555,
    "Delta": null,
    "KeyCode": null
  },
  {
    "Type": "MouseMove",
    "Time": 335,
    "X": 711,
    "Y": 549,
    "Delta": null,
    "KeyCode": null
  },
  {
    "Type": "MouseMove",
    "Time": 364,
    "X": 696,
    "Y": 525,
    "Delta": null,
    "KeyCode": null
  },
  {
    "Type": "MouseMove",
    "Time": 367,
    "X": 687,
    "Y": 516,
    "Delta": null,
    "KeyCode": null
  },
  {
    "Type": "MouseMove",
    "Time": 395,
    "X": 663,
    "Y": 495,
    "Delta": null,
    "KeyCode": null
  },
  {
    "Type": "MouseMove",
    "Time": 417,
    "X": 639,
    "Y": 483,
    "Delta": null,
    "KeyCode": null
  },
  {
    "Type": "MouseMove",
    "Time": 440,
    "X": 621,
    "Y": 477,
    "Delta": null,
    "KeyCode": null
  },
  {
    "Type": "MouseMove",
    "Time": 449,
    "X": 615,
    "Y": 474,
    "Delta": null,
    "KeyCode": null
  },
  {
    "Type": "MouseMove",
    "Time": 455,
    "X": 609,
    "Y": 471,
    "Delta": null,
    "KeyCode": null
  },
  {
    "Type": "MouseMove",
    "Time": 465,
    "X": 606,
    "Y": 471,
    "Delta": null,
    "KeyCode": null
  },
  {
    "Type": "MouseMove",
    "Time": 488,
    "X": 600,
    "Y": 468,
    "Delta": null,
    "KeyCode": null
  },
  {
    "Type": "MouseMove",
    "Time": 489,
    "X": 597,
    "Y": 468,
    "Delta": null,
    "KeyCode": null
  },
  {
    "Type": "MouseMove",
    "Time": 497,
    "X": 594,
    "Y": 468,
    "Delta": null,
    "KeyCode": null
  },
  {
    "Type": "MouseMove",
    "Time": 520,
    "X": 588,
    "Y": 468,
    "Delta": null,
    "KeyCode": null
  },
  {
    "Type": "MouseMove",
    "Time": 543,
    "X": 576,
    "Y": 468,
    "Delta": null,
    "KeyCode": null
  },
  {
    "Type": "MouseMove",
    "Time": 552,
    "X": 570,
    "Y": 468,
    "Delta": null,
    "KeyCode": null
  },
  {
    "Type": "MouseMove",
    "Time": 553,
    "X": 567,
    "Y": 468,
    "Delta": null,
    "KeyCode": null
  },
  {
    "Type": "MouseMove",
    "Time": 561,
    "X": 561,
    "Y": 468,
    "Delta": null,
    "KeyCode": null
  },
  {
    "Type": "MouseMove",
    "Time": 569,
    "X": 558,
    "Y": 468,
    "Delta": null,
    "KeyCode": null
  },
  {
    "Type": "MouseMove",
    "Time": 577,
    "X": 555,
    "Y": 468,
    "Delta": null,
    "KeyCode": null
  },
  {
    "Type": "MouseMove",
    "Time": 585,
    "X": 552,
    "Y": 465,
    "Delta": null,
    "KeyCode": null
  },
  {
    "Type": "MouseMove",
    "Time": 614,
    "X": 537,
    "Y": 462,
    "Delta": null,
    "KeyCode": null
  },
  {
    "Type": "MouseMove",
    "Time": 635,
    "X": 525,
    "Y": 462,
    "Delta": null,
    "KeyCode": null
  },
  {
    "Type": "MouseMove",
    "Time": 661,
    "X": 519,
    "Y": 459,
    "Delta": null,
    "KeyCode": null
  },
  {
    "Type": "MouseMove",
    "Time": 682,
    "X": 516,
    "Y": 459,
    "Delta": null,
    "KeyCode": null
  },
  {
    "Type": "DragStart",
    "Time": 920,
    "X": 516,
    "Y": 459,
    "Delta": null,
    "KeyCode": null
  },
  {
    "Type": "DragEnd",
    "Time": 992,
    "X": 516,
    "Y": 459,
    "Delta": null,
    "KeyCode": null
  },
  {
    "Type": "MouseMove",
    "Time": 1848,
    "X": 516,
    "Y": 456,
    "Delta": null,
    "KeyCode": null
  },
  {
    "Type": "MouseMove",
    "Time": 2268,
    "X": 510,
    "Y": 456,
    "Delta": null,
    "KeyCode": null
  },
  {
    "Type": "MouseMove",
    "Time": 2269,
    "X": 507,
    "Y": 456,
    "Delta": null,
    "KeyCode": null
  },
  {
    "Type": "MouseMove",
    "Time": 2277,
    "X": 504,
    "Y": 453,
    "Delta": null,
    "KeyCode": null
  },
  {
    "Type": "MouseMove",
    "Time": 2453,
    "X": 501,
    "Y": 453,
    "Delta": null,
    "KeyCode": null
  },
  {
    "Type": "MouseMove",
    "Time": 2469,
    "X": 498,
    "Y": 453,
    "Delta": null,
    "KeyCode": null
  },
  {
    "Type": "MouseMove",
    "Time": 2493,
    "X": 492,
    "Y": 453,
    "Delta": null,
    "KeyCode": null
  },
  {
    "Type": "MouseMove",
    "Time": 2494,
    "X": 489,
    "Y": 453,
    "Delta": null,
    "KeyCode": null
  },
  {
    "Type": "MouseMove",
    "Time": 2503,
    "X": 486,
    "Y": 453,
    "Delta": null,
    "KeyCode": null
  },
  {
    "Type": "MouseMove",
    "Time": 2511,
    "X": 480,
    "Y": 453,
    "Delta": null,
    "KeyCode": null
  },
  {
    "Type": "MouseMove",
    "Time": 2540,
    "X": 471,
    "Y": 453,
    "Delta": null,
    "KeyCode": null
  },
  {
    "Type": "MouseMove",
    "Time": 2565,
    "X": 462,
    "Y": 453,
    "Delta": null,
    "KeyCode": null
  },
  {
    "Type": "MouseMove",
    "Time": 2567,
    "X": 459,
    "Y": 453,
    "Delta": null,
    "KeyCode": null
  },
  {
    "Type": "MouseMove",
    "Time": 2575,
    "X": 456,
    "Y": 453,
    "Delta": null,
    "KeyCode": null
  },
  {
    "Type": "MouseMove",
    "Time": 2583,
    "X": 453,
    "Y": 453,
    "Delta": null,
    "KeyCode": null
  },
  {
    "Type": "MouseMove",
    "Time": 2618,
    "X": 450,
    "Y": 450,
    "Delta": null,
    "KeyCode": null
  },
  {
    "Type": "MouseMove",
    "Time": 2623,
    "X": 447,
    "Y": 450,
    "Delta": null,
    "KeyCode": null
  },
  {
    "Type": "MouseMove",
    "Time": 2647,
    "X": 444,
    "Y": 447,
    "Delta": null,
    "KeyCode": null
  },
  {
    "Type": "MouseMove",
    "Time": 2670,
    "X": 438,
    "Y": 447,
    "Delta": null,
    "KeyCode": null
  },
  {
    "Type": "MouseMove",
    "Time": 2671,
    "X": 435,
    "Y": 447,
    "Delta": null,
    "KeyCode": null
  },
  {
    "Type": "MouseMove",
    "Time": 2679,
    "X": 432,
    "Y": 447,
    "Delta": null,
    "KeyCode": null
  },
  {
    "Type": "MouseMove",
    "Time": 2687,
    "X": 429,
    "Y": 447,
    "Delta": null,
    "KeyCode": null
  },
  {
    "Type": "MouseMove",
    "Time": 2711,
    "X": 426,
    "Y": 444,
    "Delta": null,
    "KeyCode": null
  },
  {
    "Type": "MouseMove",
    "Time": 2738,
    "X": 420,
    "Y": 444,
    "Delta": null,
    "KeyCode": null
  },
  {
    "Type": "MouseMove",
    "Time": 2743,
    "X": 417,
    "Y": 444,
    "Delta": null,
    "KeyCode": null
  },
  {
    "Type": "MouseMove",
    "Time": 2774,
    "X": 408,
    "Y": 444,
    "Delta": null,
    "KeyCode": null
  },
  {
    "Type": "MouseMove",
    "Time": 2797,
    "X": 396,
    "Y": 447,
    "Delta": null,
    "KeyCode": null
  },
  {
    "Type": "MouseMove",
    "Time": 2828,
    "X": 393,
    "Y": 450,
    "Delta": null,
    "KeyCode": null
  },
  {
    "Type": "MouseMove",
    "Time": 2853,
    "X": 390,
    "Y": 450,
    "Delta": null,
    "KeyCode": null
  },
  {
    "Type": "MouseMove",
    "Time": 3124,
    "X": 387,
    "Y": 450,
    "Delta": null,
    "KeyCode": null
  },
  {
    "Type": "MouseMove",
    "Time": 3355,
    "X": 384,
    "Y": 450,
    "Delta": null,
    "KeyCode": null
  },
  {
    "Type": "DragStart",
    "Time": 4200,
    "X": 384,
    "Y": 450,
    "Delta": null,
    "KeyCode": null
  },
  {
    "Type": "DragEnd",
    "Time": 4274,
    "X": 384,
    "Y": 450,
    "Delta": null,
    "KeyCode": null
  },
  {
    "Type": "MouseMove",
    "Time": 4766,
    "X": 390,
    "Y": 450,
    "Delta": null,
    "KeyCode": null
  },
  {
    "Type": "MouseMove",
    "Time": 4789,
    "X": 396,
    "Y": 447,
    "Delta": null,
    "KeyCode": null
  },
  {
    "Type": "MouseMove",
    "Time": 4789,
    "X": 402,
    "Y": 444,
    "Delta": null,
    "KeyCode": null
  },
  {
    "Type": "MouseMove",
    "Time": 4797,
    "X": 408,
    "Y": 444,
    "Delta": null,
    "KeyCode": null
  },
  {
    "Type": "MouseMove",
    "Time": 4823,
    "X": 420,
    "Y": 438,
    "Delta": null,
    "KeyCode": null
  },
  {
    "Type": "MouseMove",
    "Time": 4829,
    "X": 423,
    "Y": 435,
    "Delta": null,
    "KeyCode": null
  },
  {
    "Type": "MouseMove",
    "Time": 4854,
    "X": 429,
    "Y": 432,
    "Delta": null,
    "KeyCode": null
  },
  {
    "Type": "MouseMove",
    "Time": 4877,
    "X": 441,
    "Y": 429,
    "Delta": null,
    "KeyCode": null
  },
  {
    "Type": "MouseMove",
    "Time": 4879,
    "X": 444,
    "Y": 426,
    "Delta": null,
    "KeyCode": null
  },
  {
    "Type": "MouseMove",
    "Time": 4902,
    "X": 456,
    "Y": 423,
    "Delta": null,
    "KeyCode": null
  },
  {
    "Type": "MouseMove",
    "Time": 4923,
    "X": 468,
    "Y": 417,
    "Delta": null,
    "KeyCode": null
  },
  {
    "Type": "MouseMove",
    "Time": 4949,
    "X": 477,
    "Y": 414,
    "Delta": null,
    "KeyCode": null
  },
  {
    "Type": "MouseMove",
    "Time": 4971,
    "X": 477,
    "Y": 411,
    "Delta": null,
    "KeyCode": null
  },
  {
    "Type": "MouseMove",
    "Time": 5041,
    "X": 477,
    "Y": 408,
    "Delta": null,
    "KeyCode": null
  },
  {
    "Type": "MouseMove",
    "Time": 5047,
    "X": 477,
    "Y": 405,
    "Delta": null,
    "KeyCode": null
  },
  {
    "Type": "MouseMove",
    "Time": 5072,
    "X": 477,
    "Y": 399,
    "Delta": null,
    "KeyCode": null
  },
  {
    "Type": "MouseMove",
    "Time": 5095,
    "X": 477,
    "Y": 396,
    "Delta": null,
    "KeyCode": null
  },
  {
    "Type": "MouseMove",
    "Time": 5185,
    "X": 477,
    "Y": 393,
    "Delta": null,
    "KeyCode": null
  },
  {
    "Type": "MouseMove",
    "Time": 5207,
    "X": 474,
    "Y": 390,
    "Delta": null,
    "KeyCode": null
  },
  {
    "Type": "MouseMove",
    "Time": 5230,
    "X": 468,
    "Y": 384,
    "Delta": null,
    "KeyCode": null
  },
  {
    "Type": "MouseMove",
    "Time": 5251,
    "X": 468,
    "Y": 375,
    "Delta": null,
    "KeyCode": null
  },
  {
    "Type": "MouseMove",
    "Time": 5273,
    "X": 468,
    "Y": 369,
    "Delta": null,
    "KeyCode": null
  },
  {
    "Type": "MouseMove",
    "Time": 5281,
    "X": 468,
    "Y": 366,
    "Delta": null,
    "KeyCode": null
  },
  {
    "Type": "MouseMove",
    "Time": 5289,
    "X": 468,
    "Y": 360,
    "Delta": null,
    "KeyCode": null
  },
  {
    "Type": "MouseMove",
    "Time": 5321,
    "X": 468,
    "Y": 357,
    "Delta": null,
    "KeyCode": null
  },
  {
    "Type": "MouseMove",
    "Time": 5321,
    "X": 468,
    "Y": 354,
    "Delta": null,
    "KeyCode": null
  },
  {
    "Type": "MouseMove",
    "Time": 5406,
    "X": 486,
    "Y": 336,
    "Delta": null,
    "KeyCode": null
  },
  {
    "Type": "MouseMove",
    "Time": 5411,
    "X": 498,
    "Y": 333,
    "Delta": null,
    "KeyCode": null
  },
  {
    "Type": "MouseMove",
    "Time": 5417,
    "X": 507,
    "Y": 327,
    "Delta": null,
    "KeyCode": null
  },
  {
    "Type": "MouseMove",
    "Time": 5445,
    "X": 549,
    "Y": 315,
    "Delta": null,
    "KeyCode": null
  },
  {
    "Type": "MouseMove",
    "Time": 5451,
    "X": 564,
    "Y": 312,
    "Delta": null,
    "KeyCode": null
  },
  {
    "Type": "MouseMove",
    "Time": 5477,
    "X": 588,
    "Y": 306,
    "Delta": null,
    "KeyCode": null
  },
  {
    "Type": "MouseMove",
    "Time": 5483,
    "X": 597,
    "Y": 306,
    "Delta": null,
    "KeyCode": null
  },
  {
    "Type": "MouseMove",
    "Time": 5507,
    "X": 618,
    "Y": 303,
    "Delta": null,
    "KeyCode": null
  },
  {
    "Type": "MouseMove",
    "Time": 5515,
    "X": 624,
    "Y": 303,
    "Delta": null,
    "KeyCode": null
  },
  {
    "Type": "MouseMove",
    "Time": 5538,
    "X": 636,
    "Y": 303,
    "Delta": null,
    "KeyCode": null
  },
  {
    "Type": "MouseMove",
    "Time": 5560,
    "X": 645,
    "Y": 306,
    "Delta": null,
    "KeyCode": null
  },
  {
    "Type": "MouseMove",
    "Time": 5563,
    "X": 648,
    "Y": 309,
    "Delta": null,
    "KeyCode": null
  },
  {
    "Type": "MouseMove",
    "Time": 5579,
    "X": 651,
    "Y": 312,
    "Delta": null,
    "KeyCode": null
  },
  {
    "Type": "MouseMove",
    "Time": 5617,
    "X": 654,
    "Y": 315,
    "Delta": null,
    "KeyCode": null
  },
  {
    "Type": "MouseMove",
    "Time": 5639,
    "X": 657,
    "Y": 318,
    "Delta": null,
    "KeyCode": null
  },
  {
    "Type": "MouseMove",
    "Time": 5651,
    "X": 657,
    "Y": 321,
    "Delta": null,
    "KeyCode": null
  },
  {
    "Type": "MouseMove",
    "Time": 5683,
    "X": 660,
    "Y": 324,
    "Delta": null,
    "KeyCode": null
  },
  {
    "Type": "MouseMove",
    "Time": 5745,
    "X": 660,
    "Y": 327,
    "Delta": null,
    "KeyCode": null
  },
  {
    "Type": "MouseMove",
    "Time": 5777,
    "X": 663,
    "Y": 330,
    "Delta": null,
    "KeyCode": null
  },
  {
    "Type": "MouseMove",
    "Time": 5800,
    "X": 666,
    "Y": 336,
    "Delta": null,
    "KeyCode": null
  },
  {
    "Type": "MouseMove",
    "Time": 5923,
    "X": 675,
    "Y": 336,
    "Delta": null,
    "KeyCode": null
  },
  {
    "Type": "MouseMove",
    "Time": 5925,
    "X": 678,
    "Y": 336,
    "Delta": null,
    "KeyCode": null
  },
  {
    "Type": "MouseMove",
    "Time": 5933,
    "X": 684,
    "Y": 336,
    "Delta": null,
    "KeyCode": null
  },
  {
    "Type": "MouseMove",
    "Time": 5941,
    "X": 693,
    "Y": 333,
    "Delta": null,
    "KeyCode": null
  },
  {
    "Type": "MouseMove",
    "Time": 5965,
    "X": 714,
    "Y": 330,
    "Delta": null,
    "KeyCode": null
  },
  {
    "Type": "MouseMove",
    "Time": 5987,
    "X": 732,
    "Y": 324,
    "Delta": null,
    "KeyCode": null
  },
  {
    "Type": "MouseMove",
    "Time": 6010,
    "X": 741,
    "Y": 324,
    "Delta": null,
    "KeyCode": null
  },
  {
    "Type": "MouseMove",
    "Time": 6036,
    "X": 744,
    "Y": 324,
    "Delta": null,
    "KeyCode": null
  },
  {
    "Type": "MouseMove",
    "Time": 6058,
    "X": 747,
    "Y": 324,
    "Delta": null,
    "KeyCode": null
  },
  {
    "Type": "MouseMove",
    "Time": 6175,
    "X": 750,
    "Y": 324,
    "Delta": null,
    "KeyCode": null
  },
  {
    "Type": "MouseMove",
    "Time": 6215,
    "X": 753,
    "Y": 324,
    "Delta": null,
    "KeyCode": null
  },
  {
    "Type": "MouseMove",
    "Time": 6237,
    "X": 756,
    "Y": 327,
    "Delta": null,
    "KeyCode": null
  },
  {
    "Type": "MouseMove",
    "Time": 6258,
    "X": 759,
    "Y": 333,
    "Delta": null,
    "KeyCode": null
  },
  {
    "Type": "MouseMove",
    "Time": 6282,
    "X": 762,
    "Y": 336,
    "Delta": null,
    "KeyCode": null
  },
  {
    "Type": "MouseMove",
    "Time": 6304,
    "X": 762,
    "Y": 339,
    "Delta": null,
    "KeyCode": null
  },
  {
    "Type": "MouseMove",
    "Time": 6305,
    "X": 765,
    "Y": 342,
    "Delta": null,
    "KeyCode": null
  },
  {
    "Type": "MouseMove",
    "Time": 6330,
    "X": 765,
    "Y": 345,
    "Delta": null,
    "KeyCode": null
  },
  {
    "Type": "MouseMove",
    "Time": 6351,
    "X": 765,
    "Y": 348,
    "Delta": null,
    "KeyCode": null
  },
  {
    "Type": "MouseMove",
    "Time": 6378,
    "X": 765,
    "Y": 351,
    "Delta": null,
    "KeyCode": null
  },
  {
    "Type": "MouseMove",
    "Time": 6401,
    "X": 765,
    "Y": 354,
    "Delta": null,
    "KeyCode": null
  },
  {
    "Type": "MouseMove",
    "Time": 6495,
    "X": 765,
    "Y": 357,
    "Delta": null,
    "KeyCode": null
  },
  {
    "Type": "MouseMove",
    "Time": 6497,
    "X": 765,
    "Y": 360,
    "Delta": null,
    "KeyCode": null
  },
  {
    "Type": "MouseMove",
    "Time": 6660,
    "X": 768,
    "Y": 366,
    "Delta": null,
    "KeyCode": null
  },
  {
    "Type": "MouseMove",
    "Time": 6733,
    "X": 771,
    "Y": 366,
    "Delta": null,
    "KeyCode": null
  },
  {
    "Type": "MouseMove",
    "Time": 6758,
    "X": 780,
    "Y": 369,
    "Delta": null,
    "KeyCode": null
  },
  {
    "Type": "MouseMove",
    "Time": 6787,
    "X": 786,
    "Y": 369,
    "Delta": null,
    "KeyCode": null
  },
  {
    "Type": "MouseMove",
    "Time": 6795,
    "X": 789,
    "Y": 369,
    "Delta": null,
    "KeyCode": null
  },
  {
    "Type": "DragStart",
    "Time": 8905,
    "X": 789,
    "Y": 369,
    "Delta": null,
    "KeyCode": null
  },
  {
    "Type": "DragEnd",
    "Time": 8998,
    "X": 789,
    "Y": 369,
    "Delta": null,
    "KeyCode": null
  },
  {
    "Type": "MouseMove",
    "Time": 9042,
    "X": 792,
    "Y": 366,
    "Delta": null,
    "KeyCode": null
  },
  {
    "Type": "MouseMove",
    "Time": 9571,
    "X": 786,
    "Y": 366,
    "Delta": null,
    "KeyCode": null
  },
  {
    "Type": "MouseMove",
    "Time": 9595,
    "X": 774,
    "Y": 366,
    "Delta": null,
    "KeyCode": null
  },
  {
    "Type": "MouseMove",
    "Time": 9623,
    "X": 762,
    "Y": 372,
    "Delta": null,
    "KeyCode": null
  },
  {
    "Type": "MouseMove",
    "Time": 9623,
    "X": 756,
    "Y": 372,
    "Delta": null,
    "KeyCode": null
  },
  {
    "Type": "MouseMove",
    "Time": 9631,
    "X": 753,
    "Y": 372,
    "Delta": null,
    "KeyCode": null
  },
  {
    "Type": "MouseMove",
    "Time": 9639,
    "X": 750,
    "Y": 375,
    "Delta": null,
    "KeyCode": null
  },
  {
    "Type": "MouseMove",
    "Time": 9647,
    "X": 741,
    "Y": 378,
    "Delta": null,
    "KeyCode": null
  },
  {
    "Type": "MouseMove",
    "Time": 9681,
    "X": 696,
    "Y": 396,
    "Delta": null,
    "KeyCode": null
  },
  {
    "Type": "MouseMove",
    "Time": 9708,
    "X": 663,
    "Y": 411,
    "Delta": null,
    "KeyCode": null
  },
  {
    "Type": "MouseMove",
    "Time": 9731,
    "X": 645,
    "Y": 423,
    "Delta": null,
    "KeyCode": null
  },
  {
    "Type": "MouseMove",
    "Time": 9735,
    "X": 639,
    "Y": 426,
    "Delta": null,
    "KeyCode": null
  },
  {
    "Type": "MouseMove",
    "Time": 9743,
    "X": 633,
    "Y": 429,
    "Delta": null,
    "KeyCode": null
  },
  {
    "Type": "MouseMove",
    "Time": 9774,
    "X": 621,
    "Y": 438,
    "Delta": null,
    "KeyCode": null
  },
  {
    "Type": "MouseMove",
    "Time": 9798,
    "X": 606,
    "Y": 447,
    "Delta": null,
    "KeyCode": null
  },
  {
    "Type": "MouseMove",
    "Time": 9824,
    "X": 597,
    "Y": 453,
    "Delta": null,
    "KeyCode": null
  },
  {
    "Type": "MouseMove",
    "Time": 9847,
    "X": 594,
    "Y": 456,
    "Delta": null,
    "KeyCode": null
  },
  {
    "Type": "MouseMove",
    "Time": 9872,
    "X": 588,
    "Y": 462,
    "Delta": null,
    "KeyCode": null
  },
  {
    "Type": "MouseMove",
    "Time": 9900,
    "X": 570,
    "Y": 474,
    "Delta": null,
    "KeyCode": null
  },
  {
    "Type": "MouseMove",
    "Time": 9924,
    "X": 561,
    "Y": 480,
    "Delta": null,
    "KeyCode": null
  },
  {
    "Type": "MouseMove",
    "Time": 9951,
    "X": 558,
    "Y": 480,
    "Delta": null,
    "KeyCode": null
  },
  {
    "Type": "MouseMove",
    "Time": 10032,
    "X": 555,
    "Y": 480,
    "Delta": null,
    "KeyCode": null
  },
  {
    "Type": "MouseMove",
    "Time": 10041,
    "X": 552,
    "Y": 480,
    "Delta": null,
    "KeyCode": null
  },
  {
    "Type": "MouseMove",
    "Time": 10245,
    "X": 549,
    "Y": 480,
    "Delta": null,
    "KeyCode": null
  },
  {
    "Type": "MouseMove",
    "Time": 10269,
    "X": 549,
    "Y": 477,
    "Delta": null,
    "KeyCode": null
  },
  {
    "Type": "MouseMove",
    "Time": 10294,
    "X": 546,
    "Y": 474,
    "Delta": null,
    "KeyCode": null
  },
  {
    "Type": "MouseMove",
    "Time": 10358,
    "X": 546,
    "Y": 471,
    "Delta": null,
    "KeyCode": null
  },
  {
    "Type": "MouseMove",
    "Time": 10551,
    "X": 540,
    "Y": 471,
    "Delta": null,
    "KeyCode": null
  },
  {
    "Type": "MouseMove",
    "Time": 10576,
    "X": 534,
    "Y": 474,
    "Delta": null,
    "KeyCode": null
  },
  {
    "Type": "MouseMove",
    "Time": 10601,
    "X": 522,
    "Y": 477,
    "Delta": null,
    "KeyCode": null
  },
  {
    "Type": "MouseMove",
    "Time": 10630,
    "X": 507,
    "Y": 480,
    "Delta": null,
    "KeyCode": null
  },
  {
    "Type": "MouseMove",
    "Time": 10657,
    "X": 504,
    "Y": 480,
    "Delta": null,
    "KeyCode": null
  },
  {
    "Type": "MouseMove",
    "Time": 10805,
    "X": 504,
    "Y": 483,
    "Delta": null,
    "KeyCode": null
  },
  {
    "Type": "MouseMove",
    "Time": 11349,
    "X": 501,
    "Y": 483,
    "Delta": null,
    "KeyCode": null
  },
  {
    "Type": "DragStart",
    "Time": 13194,
    "X": 501,
    "Y": 483,
    "Delta": null,
    "KeyCode": null
  },
  {
    "Type": "DragEnd",
    "Time": 13279,
    "X": 501,
    "Y": 483,
    "Delta": null,
    "KeyCode": null
  },
  {
    "Type": "MouseMove",
    "Time": 14675,
    "X": 501,
    "Y": 471,
    "Delta": null,
    "KeyCode": null
  },
  {
    "Type": "MouseMove",
    "Time": 14701,
    "X": 501,
    "Y": 450,
    "Delta": null,
    "KeyCode": null
  },
  {
    "Type": "MouseMove",
    "Time": 14727,
    "X": 516,
    "Y": 405,
    "Delta": null,
    "KeyCode": null
  },
  {
    "Type": "MouseMove",
    "Time": 14749,
    "X": 537,
    "Y": 354,
    "Delta": null,
    "KeyCode": null
  },
  {
    "Type": "MouseMove",
    "Time": 14772,
    "X": 555,
    "Y": 318,
    "Delta": null,
    "KeyCode": null
  },
  {
    "Type": "MouseMove",
    "Time": 14772,
    "X": 561,
    "Y": 300,
    "Delta": null,
    "KeyCode": null
  },
  {
    "Type": "MouseMove",
    "Time": 14777,
    "X": 573,
    "Y": 279,
    "Delta": null,
    "KeyCode": null
  },
  {
    "Type": "MouseMove",
    "Time": 14787,
    "X": 582,
    "Y": 264,
    "Delta": null,
    "KeyCode": null
  },
  {
    "Type": "MouseMove",
    "Time": 14793,
    "X": 588,
    "Y": 252,
    "Delta": null,
    "KeyCode": null
  },
  {
    "Type": "MouseMove",
    "Time": 14822,
    "X": 609,
    "Y": 216,
    "Delta": null,
    "KeyCode": null
  },
  {
    "Type": "MouseMove",
    "Time": 14827,
    "X": 612,
    "Y": 207,
    "Delta": null,
    "KeyCode": null
  },
  {
    "Type": "MouseMove",
    "Time": 14854,
    "X": 630,
    "Y": 174,
    "Delta": null,
    "KeyCode": null
  },
  {
    "Type": "MouseMove",
    "Time": 14876,
    "X": 645,
    "Y": 150,
    "Delta": null,
    "KeyCode": null
  },
  {
    "Type": "MouseMove",
    "Time": 14901,
    "X": 654,
    "Y": 132,
    "Delta": null,
    "KeyCode": null
  },
  {
    "Type": "MouseMove",
    "Time": 14907,
    "X": 657,
    "Y": 126,
    "Delta": null,
    "KeyCode": null
  },
  {
    "Type": "MouseMove",
    "Time": 14933,
    "X": 660,
    "Y": 114,
    "Delta": null,
    "KeyCode": null
  },
  {
    "Type": "MouseMove",
    "Time": 14939,
    "X": 663,
    "Y": 108,
    "Delta": null,
    "KeyCode": null
  },
  {
    "Type": "MouseMove",
    "Time": 14963,
    "X": 675,
    "Y": 87,
    "Delta": null,
    "KeyCode": null
  },
  {
    "Type": "MouseMove",
    "Time": 14986,
    "X": 681,
    "Y": 72,
    "Delta": null,
    "KeyCode": null
  },
  {
    "Type": "MouseMove",
    "Time": 15010,
    "X": 687,
    "Y": 63,
    "Delta": null,
    "KeyCode": null
  },
  {
    "Type": "MouseMove",
    "Time": 15011,
    "X": 687,
    "Y": 60,
    "Delta": null,
    "KeyCode": null
  },
  {
    "Type": "MouseMove",
    "Time": 15044,
    "X": 690,
    "Y": 54,
    "Delta": null,
    "KeyCode": null
  },
  {
    "Type": "MouseMove",
    "Time": 15069,
    "X": 690,
    "Y": 51,
    "Delta": null,
    "KeyCode": null
  },
  {
    "Type": "MouseMove",
    "Time": 15070,
    "X": 693,
    "Y": 48,
    "Delta": null,
    "KeyCode": null
  },
  {
    "Type": "MouseMove",
    "Time": 15096,
    "X": 696,
    "Y": 36,
    "Delta": null,
    "KeyCode": null
  },
  {
    "Type": "MouseMove",
    "Time": 15122,
    "X": 699,
    "Y": 36,
    "Delta": null,
    "KeyCode": null
  },
  {
    "Type": "MouseMove",
    "Time": 15146,
    "X": 699,
    "Y": 33,
    "Delta": null,
    "KeyCode": null
  },
  {
    "Type": "MouseMove",
    "Time": 15169,
    "X": 702,
    "Y": 27,
    "Delta": null,
    "KeyCode": null
  },
  {
    "Type": "MouseMove",
    "Time": 15194,
    "X": 702,
    "Y": 24,
    "Delta": null,
    "KeyCode": null
  },
  {
    "Type": "MouseMove",
    "Time": 15220,
    "X": 705,
    "Y": 21,
    "Delta": null,
    "KeyCode": null
  },
  {
    "Type": "MouseMove",
    "Time": 15340,
    "X": 708,
    "Y": 18,
    "Delta": null,
    "KeyCode": null
  },
  {
    "Type": "MouseMove",
    "Time": 16381,
    "X": 702,
    "Y": 18,
    "Delta": null,
    "KeyCode": null
  },
  {
    "Type": "MouseMove",
    "Time": 16413,
    "X": 687,
    "Y": 57,
    "Delta": null,
    "KeyCode": null
  },
  {
    "Type": "MouseMove",
    "Time": 16414,
    "X": 678,
    "Y": 81,
    "Delta": null,
    "KeyCode": null
  },
  {
    "Type": "MouseMove",
    "Time": 16444,
    "X": 645,
    "Y": 141,
    "Delta": null,
    "KeyCode": null
  },
  {
    "Type": "MouseMove",
    "Time": 16469,
    "X": 600,
    "Y": 210,
    "Delta": null,
    "KeyCode": null
  },
  {
    "Type": "MouseMove",
    "Time": 16494,
    "X": 552,
    "Y": 267,
    "Delta": null,
    "KeyCode": null
  },
  {
    "Type": "MouseMove",
    "Time": 16527,
    "X": 522,
    "Y": 300,
    "Delta": null,
    "KeyCode": null
  },
  {
    "Type": "MouseMove",
    "Time": 16550,
    "X": 495,
    "Y": 324,
    "Delta": null,
    "KeyCode": null
  },
  {
    "Type": "MouseMove",
    "Time": 16574,
    "X": 480,
    "Y": 339,
    "Delta": null,
    "KeyCode": null
  },
  {
    "Type": "MouseMove",
    "Time": 16575,
    "X": 474,
    "Y": 342,
    "Delta": null,
    "KeyCode": null
  },
  {
    "Type": "MouseMove",
    "Time": 16583,
    "X": 471,
    "Y": 342,
    "Delta": null,
    "KeyCode": null
  },
  {
    "Type": "MouseMove",
    "Time": 16616,
    "X": 462,
    "Y": 354,
    "Delta": null,
    "KeyCode": null
  },
  {
    "Type": "MouseMove",
    "Time": 16640,
    "X": 453,
    "Y": 363,
    "Delta": null,
    "KeyCode": null
  },
  {
    "Type": "MouseMove",
    "Time": 16663,
    "X": 447,
    "Y": 372,
    "Delta": null,
    "KeyCode": null
  },
  {
    "Type": "MouseMove",
    "Time": 16687,
    "X": 444,
    "Y": 378,
    "Delta": null,
    "KeyCode": null
  },
  {
    "Type": "MouseMove",
    "Time": 16711,
    "X": 441,
    "Y": 378,
    "Delta": null,
    "KeyCode": null
  },
  {
    "Type": "MouseMove",
    "Time": 16712,
    "X": 435,
    "Y": 387,
    "Delta": null,
    "KeyCode": null
  },
  {
    "Type": "MouseMove",
    "Time": 16741,
    "X": 432,
    "Y": 396,
    "Delta": null,
    "KeyCode": null
  },
  {
    "Type": "MouseMove",
    "Time": 16763,
    "X": 429,
    "Y": 408,
    "Delta": null,
    "KeyCode": null
  },
  {
    "Type": "MouseMove",
    "Time": 16792,
    "X": 423,
    "Y": 429,
    "Delta": null,
    "KeyCode": null
  },
  {
    "Type": "MouseMove",
    "Time": 16799,
    "X": 420,
    "Y": 432,
    "Delta": null,
    "KeyCode": null
  },
  {
    "Type": "MouseMove",
    "Time": 16807,
    "X": 414,
    "Y": 438,
    "Delta": null,
    "KeyCode": null
  },
  {
    "Type": "MouseMove",
    "Time": 16836,
    "X": 408,
    "Y": 450,
    "Delta": null,
    "KeyCode": null
  },
  {
    "Type": "MouseMove",
    "Time": 16860,
    "X": 402,
    "Y": 459,
    "Delta": null,
    "KeyCode": null
  },
  {
    "Type": "MouseMove",
    "Time": 16897,
    "X": 402,
    "Y": 462,
    "Delta": null,
    "KeyCode": null
  },
  {
    "Type": "MouseMove",
    "Time": 17357,
    "X": 402,
    "Y": 459,
    "Delta": null,
    "KeyCode": null
  },
  {
    "Type": "MouseMove",
    "Time": 17387,
    "X": 399,
    "Y": 459,
    "Delta": null,
    "KeyCode": null
  },
  {
    "Type": "MouseMove",
    "Time": 17660,
    "X": 396,
    "Y": 459,
    "Delta": null,
    "KeyCode": null
  },
  {
    "Type": "MouseMove",
    "Time": 17684,
    "X": 393,
    "Y": 462,
    "Delta": null,
    "KeyCode": null
  },
  {
    "Type": "MouseMove",
    "Time": 17687,
    "X": 390,
    "Y": 462,
    "Delta": null,
    "KeyCode": null
  },
  {
    "Type": "MouseMove",
    "Time": 20411,
    "X": 393,
    "Y": 459,
    "Delta": null,
    "KeyCode": null
  },
  {
    "Type": "MouseMove",
    "Time": 20433,
    "X": 405,
    "Y": 453,
    "Delta": null,
    "KeyCode": null
  },
  {
    "Type": "MouseMove",
    "Time": 20456,
    "X": 417,
    "Y": 447,
    "Delta": null,
    "KeyCode": null
  },
  {
    "Type": "MouseMove",
    "Time": 20479,
    "X": 444,
    "Y": 435,
    "Delta": null,
    "KeyCode": null
  },
  {
    "Type": "MouseMove",
    "Time": 20481,
    "X": 450,
    "Y": 435,
    "Delta": null,
    "KeyCode": null
  },
  {
    "Type": "MouseMove",
    "Time": 20489,
    "X": 459,
    "Y": 432,
    "Delta": null,
    "KeyCode": null
  },
  {
    "Type": "MouseMove",
    "Time": 20497,
    "X": 465,
    "Y": 432,
    "Delta": null,
    "KeyCode": null
  },
  {
    "Type": "MouseMove",
    "Time": 20505,
    "X": 474,
    "Y": 429,
    "Delta": null,
    "KeyCode": null
  },
  {
    "Type": "MouseMove",
    "Time": 20513,
    "X": 483,
    "Y": 426,
    "Delta": null,
    "KeyCode": null
  },
  {
    "Type": "MouseMove",
    "Time": 20544,
    "X": 504,
    "Y": 420,
    "Delta": null,
    "KeyCode": null
  },
  {
    "Type": "MouseMove",
    "Time": 20566,
    "X": 540,
    "Y": 411,
    "Delta": null,
    "KeyCode": null
  },
  {
    "Type": "MouseMove",
    "Time": 20569,
    "X": 552,
    "Y": 408,
    "Delta": null,
    "KeyCode": null
  },
  {
    "Type": "MouseMove",
    "Time": 20577,
    "X": 564,
    "Y": 402,
    "Delta": null,
    "KeyCode": null
  },
  {
    "Type": "MouseMove",
    "Time": 20603,
    "X": 591,
    "Y": 396,
    "Delta": null,
    "KeyCode": null
  },
  {
    "Type": "MouseMove",
    "Time": 20626,
    "X": 606,
    "Y": 390,
    "Delta": null,
    "KeyCode": null
  },
  {
    "Type": "MouseMove",
    "Time": 20633,
    "X": 612,
    "Y": 390,
    "Delta": null,
    "KeyCode": null
  },
  {
    "Type": "MouseMove",
    "Time": 20643,
    "X": 615,
    "Y": 387,
    "Delta": null,
    "KeyCode": null
  },
  {
    "Type": "MouseMove",
    "Time": 20667,
    "X": 624,
    "Y": 384,
    "Delta": null,
    "KeyCode": null
  },
  {
    "Type": "MouseMove",
    "Time": 20690,
    "X": 645,
    "Y": 375,
    "Delta": null,
    "KeyCode": null
  },
  {
    "Type": "MouseMove",
    "Time": 20691,
    "X": 648,
    "Y": 372,
    "Delta": null,
    "KeyCode": null
  },
  {
    "Type": "MouseMove",
    "Time": 20715,
    "X": 657,
    "Y": 372,
    "Delta": null,
    "KeyCode": null
  },
  {
    "Type": "MouseMove",
    "Time": 20738,
    "X": 660,
    "Y": 369,
    "Delta": null,
    "KeyCode": null
  },
  {
    "Type": "MouseMove",
    "Time": 21048,
    "X": 663,
    "Y": 363,
    "Delta": null,
    "KeyCode": null
  },
  {
    "Type": "DragStart",
    "Time": 21711,
    "X": 663,
    "Y": 363,
    "Delta": null,
    "KeyCode": null
  },
  {
    "Type": "DragEnd",
    "Time": 21840,
    "X": 663,
    "Y": 363,
    "Delta": null,
    "KeyCode": null
  },
  {
    "Type": "MouseMove",
    "Time": 22813,
    "X": 660,
    "Y": 366,
    "Delta": null,
    "KeyCode": null
  },
  {
    "Type": "MouseMove",
    "Time": 22817,
    "X": 657,
    "Y": 369,
    "Delta": null,
    "KeyCode": null
  },
  {
    "Type": "MouseMove",
    "Time": 22843,
    "X": 639,
    "Y": 378,
    "Delta": null,
    "KeyCode": null
  },
  {
    "Type": "MouseMove",
    "Time": 22867,
    "X": 615,
    "Y": 390,
    "Delta": null,
    "KeyCode": null
  },
  {
    "Type": "MouseMove",
    "Time": 22892,
    "X": 594,
    "Y": 402,
    "Delta": null,
    "KeyCode": null
  },
  {
    "Type": "MouseMove",
    "Time": 22918,
    "X": 579,
    "Y": 408,
    "Delta": null,
    "KeyCode": null
  },
  {
    "Type": "MouseMove",
    "Time": 22944,
    "X": 570,
    "Y": 414,
    "Delta": null,
    "KeyCode": null
  },
  {
    "Type": "MouseMove",
    "Time": 22970,
    "X": 561,
    "Y": 420,
    "Delta": null,
    "KeyCode": null
  },
  {
    "Type": "MouseMove",
    "Time": 22994,
    "X": 558,
    "Y": 420,
    "Delta": null,
    "KeyCode": null
  },
  {
    "Type": "MouseMove",
    "Time": 23017,
    "X": 558,
    "Y": 423,
    "Delta": null,
    "KeyCode": null
  },
  {
    "Type": "MouseMove",
    "Time": 23069,
    "X": 555,
    "Y": 426,
    "Delta": null,
    "KeyCode": null
  },
  {
    "Type": "MouseMove",
    "Time": 23093,
    "X": 552,
    "Y": 429,
    "Delta": null,
    "KeyCode": null
  },
  {
    "Type": "MouseMove",
    "Time": 23124,
    "X": 552,
    "Y": 432,
    "Delta": null,
    "KeyCode": null
  },
  {
    "Type": "MouseMove",
    "Time": 23149,
    "X": 549,
    "Y": 432,
    "Delta": null,
    "KeyCode": null
  },
  {
    "Type": "MouseMove",
    "Time": 23174,
    "X": 546,
    "Y": 435,
    "Delta": null,
    "KeyCode": null
  },
  {
    "Type": "MouseMove",
    "Time": 23198,
    "X": 543,
    "Y": 438,
    "Delta": null,
    "KeyCode": null
  },
  {
    "Type": "MouseMove",
    "Time": 23226,
    "X": 543,
    "Y": 441,
    "Delta": null,
    "KeyCode": null
  },
  {
    "Type": "MouseMove",
    "Time": 23254,
    "X": 540,
    "Y": 444,
    "Delta": null,
    "KeyCode": null
  },
  {
    "Type": "MouseMove",
    "Time": 23254,
    "X": 537,
    "Y": 444,
    "Delta": null,
    "KeyCode": null
  },
  {
    "Type": "MouseMove",
    "Time": 23279,
    "X": 534,
    "Y": 447,
    "Delta": null,
    "KeyCode": null
  },
  {
    "Type": "MouseMove",
    "Time": 23304,
    "X": 534,
    "Y": 450,
    "Delta": null,
    "KeyCode": null
  },
  {
    "Type": "MouseMove",
    "Time": 23424,
    "X": 531,
    "Y": 450,
    "Delta": null,
    "KeyCode": null
  },
  {
    "Type": "MouseMove",
    "Time": 26063,
    "X": 528,
    "Y": 450,
    "Delta": null,
    "KeyCode": null
  },
  {
    "Type": "MouseMove",
    "Time": 26094,
    "X": 513,
    "Y": 453,
    "Delta": null,
    "KeyCode": null
  },
  {
    "Type": "MouseMove",
    "Time": 26117,
    "X": 483,
    "Y": 453,
    "Delta": null,
    "KeyCode": null
  },
  {
    "Type": "MouseMove",
    "Time": 26140,
    "X": 462,
    "Y": 453,
    "Delta": null,
    "KeyCode": null
  },
  {
    "Type": "MouseMove",
    "Time": 26143,
    "X": 450,
    "Y": 453,
    "Delta": null,
    "KeyCode": null
  },
  {
    "Type": "MouseMove",
    "Time": 26151,
    "X": 444,
    "Y": 453,
    "Delta": null,
    "KeyCode": null
  },
  {
    "Type": "MouseMove",
    "Time": 26159,
    "X": 438,
    "Y": 453,
    "Delta": null,
    "KeyCode": null
  },
  {
    "Type": "MouseMove",
    "Time": 26185,
    "X": 423,
    "Y": 453,
    "Delta": null,
    "KeyCode": null
  },
  {
    "Type": "MouseMove",
    "Time": 26193,
    "X": 417,
    "Y": 453,
    "Delta": null,
    "KeyCode": null
  },
  {
    "Type": "MouseMove",
    "Time": 26217,
    "X": 411,
    "Y": 453,
    "Delta": null,
    "KeyCode": null
  },
  {
    "Type": "MouseMove",
    "Time": 26400,
    "X": 408,
    "Y": 453,
    "Delta": null,
    "KeyCode": null
  },
  {
    "Type": "DragStart",
    "Time": 28916,
    "X": 408,
    "Y": 453,
    "Delta": null,
    "KeyCode": null
  },
  {
    "Type": "DragEnd",
    "Time": 29007,
    "X": 408,
    "Y": 453,
    "Delta": null,
    "KeyCode": null
  },
  {
    "Type": "MouseMove",
    "Time": 29055,
    "X": 408,
    "Y": 450,
    "Delta": null,
    "KeyCode": null
  },
  {
    "Type": "MouseMove",
    "Time": 30349,
    "X": 411,
    "Y": 450,
    "Delta": null,
    "KeyCode": null
  },
  {
    "Type": "MouseMove",
    "Time": 30357,
    "X": 414,
    "Y": 447,
    "Delta": null,
    "KeyCode": null
  },
  {
    "Type": "MouseMove",
    "Time": 30382,
    "X": 420,
    "Y": 444,
    "Delta": null,
    "KeyCode": null
  },
  {
    "Type": "MouseMove",
    "Time": 30403,
    "X": 423,
    "Y": 444,
    "Delta": null,
    "KeyCode": null
  },
  {
    "Type": "MouseMove",
    "Time": 30413,
    "X": 426,
    "Y": 444,
    "Delta": null,
    "KeyCode": null
  },
  {
    "Type": "MouseMove",
    "Time": 30447,
    "X": 435,
    "Y": 444,
    "Delta": null,
    "KeyCode": null
  },
  {
    "Type": "MouseMove",
    "Time": 30472,
    "X": 459,
    "Y": 441,
    "Delta": null,
    "KeyCode": null
  },
  {
    "Type": "MouseMove",
    "Time": 30494,
    "X": 486,
    "Y": 435,
    "Delta": null,
    "KeyCode": null
  },
  {
    "Type": "MouseMove",
    "Time": 30517,
    "X": 501,
    "Y": 435,
    "Delta": null,
    "KeyCode": null
  },
  {
    "Type": "MouseMove",
    "Time": 30518,
    "X": 507,
    "Y": 435,
    "Delta": null,
    "KeyCode": null
  },
  {
    "Type": "MouseMove",
    "Time": 30541,
    "X": 525,
    "Y": 435,
    "Delta": null,
    "KeyCode": null
  },
  {
    "Type": "MouseMove",
    "Time": 30565,
    "X": 540,
    "Y": 435,
    "Delta": null,
    "KeyCode": null
  },
  {
    "Type": "MouseMove",
    "Time": 30590,
    "X": 549,
    "Y": 435,
    "Delta": null,
    "KeyCode": null
  },
  {
    "Type": "MouseMove",
    "Time": 30590,
    "X": 570,
    "Y": 435,
    "Delta": null,
    "KeyCode": null
  },
  {
    "Type": "MouseMove",
    "Time": 30613,
    "X": 576,
    "Y": 435,
    "Delta": null,
    "KeyCode": null
  },
  {
    "Type": "MouseMove",
    "Time": 30613,
    "X": 594,
    "Y": 432,
    "Delta": null,
    "KeyCode": null
  },
  {
    "Type": "MouseMove",
    "Time": 30636,
    "X": 612,
    "Y": 432,
    "Delta": null,
    "KeyCode": null
  },
  {
    "Type": "MouseMove",
    "Time": 30645,
    "X": 615,
    "Y": 432,
    "Delta": null,
    "KeyCode": null
  },
  {
    "Type": "MouseMove",
    "Time": 31256,
    "X": 624,
    "Y": 435,
    "Delta": null,
    "KeyCode": null
  },
  {
    "Type": "MouseMove",
    "Time": 31259,
    "X": 624,
    "Y": 438,
    "Delta": null,
    "KeyCode": null
  },
  {
    "Type": "MouseMove",
    "Time": 31291,
    "X": 627,
    "Y": 441,
    "Delta": null,
    "KeyCode": null
  },
  {
    "Type": "MouseMove",
    "Time": 31317,
    "X": 630,
    "Y": 441,
    "Delta": null,
    "KeyCode": null
  },
  {
    "Type": "MouseMove",
    "Time": 31347,
    "X": 639,
    "Y": 444,
    "Delta": null,
    "KeyCode": null
  },
  {
    "Type": "MouseMove",
    "Time": 31370,
    "X": 642,
    "Y": 447,
    "Delta": null,
    "KeyCode": null
  },
  {
    "Type": "MouseMove",
    "Time": 31634,
    "X": 645,
    "Y": 450,
    "Delta": null,
    "KeyCode": null
  },
  {
    "Type": "MouseMove",
    "Time": 33073,
    "X": 645,
    "Y": 453,
    "Delta": null,
    "KeyCode": null
  },
  {
    "Type": "MouseMove",
    "Time": 33161,
    "X": 645,
    "Y": 456,
    "Delta": null,
    "KeyCode": null
  },
  {
    "Type": "MouseMove",
    "Time": 33167,
    "X": 648,
    "Y": 456,
    "Delta": null,
    "KeyCode": null
  },
  {
    "Type": "MouseMove",
    "Time": 33212,
    "X": 648,
    "Y": 459,
    "Delta": null,
    "KeyCode": null
  },
  {
    "Type": "MouseMove",
    "Time": 33240,
    "X": 648,
    "Y": 462,
    "Delta": null,
    "KeyCode": null
  },
  {
    "Type": "MouseMove",
    "Time": 33352,
    "X": 648,
    "Y": 465,
    "Delta": null,
    "KeyCode": null
  },
  {
    "Type": "MouseMove",
    "Time": 33393,
    "X": 648,
    "Y": 468,
    "Delta": null,
    "KeyCode": null
  },
  {
    "Type": "MouseMove",
    "Time": 33401,
    "X": 651,
    "Y": 468,
    "Delta": null,
    "KeyCode": null
  },
  {
    "Type": "DragStart",
    "Time": 33720,
    "X": 651,
    "Y": 468,
    "Delta": null,
    "KeyCode": null
  },
  {
    "Type": "DragEnd",
    "Time": 33843,
    "X": 651,
    "Y": 468,
    "Delta": null,
    "KeyCode": null
  },
  {
    "Type": "MouseMove",
    "Time": 36761,
    "X": 651,
    "Y": 465,
    "Delta": null,
    "KeyCode": null
  },
  {
    "Type": "MouseMove",
    "Time": 36784,
    "X": 651,
    "Y": 462,
    "Delta": null,
    "KeyCode": null
  },
  {
    "Type": "MouseMove",
    "Time": 36809,
    "X": 651,
    "Y": 459,
    "Delta": null,
    "KeyCode": null
  },
  {
    "Type": "MouseMove",
    "Time": 36835,
    "X": 651,
    "Y": 453,
    "Delta": null,
    "KeyCode": null
  },
  {
    "Type": "MouseMove",
    "Time": 36841,
    "X": 651,
    "Y": 450,
    "Delta": null,
    "KeyCode": null
  },
  {
    "Type": "MouseMove",
    "Time": 36866,
    "X": 651,
    "Y": 441,
    "Delta": null,
    "KeyCode": null
  },
  {
    "Type": "MouseMove",
    "Time": 36888,
    "X": 651,
    "Y": 435,
    "Delta": null,
    "KeyCode": null
  },
  {
    "Type": "MouseMove",
    "Time": 36889,
    "X": 651,
    "Y": 432,
    "Delta": null,
    "KeyCode": null
  },
  {
    "Type": "MouseMove",
    "Time": 36906,
    "X": 651,
    "Y": 429,
    "Delta": null,
    "KeyCode": null
  },
  {
    "Type": "MouseMove",
    "Time": 36929,
    "X": 651,
    "Y": 426,
    "Delta": null,
    "KeyCode": null
  },
  {
    "Type": "MouseMove",
    "Time": 36937,
    "X": 651,
    "Y": 423,
    "Delta": null,
    "KeyCode": null
  },
  {
    "Type": "MouseMove",
    "Time": 36964,
    "X": 651,
    "Y": 414,
    "Delta": null,
    "KeyCode": null
  },
  {
    "Type": "MouseMove",
    "Time": 36990,
    "X": 651,
    "Y": 411,
    "Delta": null,
    "KeyCode": null
  },
  {
    "Type": "MouseMove",
    "Time": 36993,
    "X": 651,
    "Y": 408,
    "Delta": null,
    "KeyCode": null
  },
  {
    "Type": "MouseMove",
    "Time": 37021,
    "X": 651,
    "Y": 402,
    "Delta": null,
    "KeyCode": null
  },
  {
    "Type": "MouseMove",
    "Time": 37045,
    "X": 651,
    "Y": 399,
    "Delta": null,
    "KeyCode": null
  },
  {
    "Type": "MouseMove",
    "Time": 37069,
    "X": 651,
    "Y": 396,
    "Delta": null,
    "KeyCode": null
  },
  {
    "Type": "MouseMove",
    "Time": 37083,
    "X": 651,
    "Y": 393,
    "Delta": null,
    "KeyCode": null
  },
  {
    "Type": "MouseMove",
    "Time": 37115,
    "X": 651,
    "Y": 387,
    "Delta": null,
    "KeyCode": null
  },
  {
    "Type": "MouseMove",
    "Time": 37123,
    "X": 654,
    "Y": 384,
    "Delta": null,
    "KeyCode": null
  },
  {
    "Type": "MouseMove",
    "Time": 37139,
    "X": 654,
    "Y": 381,
    "Delta": null,
    "KeyCode": null
  },
  {
    "Type": "MouseMove",
    "Time": 37164,
    "X": 654,
    "Y": 378,
    "Delta": null,
    "KeyCode": null
  },
  {
    "Type": "MouseMove",
    "Time": 37186,
    "X": 654,
    "Y": 375,
    "Delta": null,
    "KeyCode": null
  },
  {
    "Type": "MouseMove",
    "Time": 37195,
    "X": 654,
    "Y": 372,
    "Delta": null,
    "KeyCode": null
  },
  {
    "Type": "MouseMove",
    "Time": 37247,
    "X": 654,
    "Y": 369,
    "Delta": null,
    "KeyCode": null
  },
  {
    "Type": "MouseMove",
    "Time": 37860,
    "X": 654,
    "Y": 366,
    "Delta": null,
    "KeyCode": null
  },
  {
    "Type": "DragStart",
    "Time": 41483,
    "X": 654,
    "Y": 366,
    "Delta": null,
    "KeyCode": null
  },
  {
    "Type": "DragEnd",
    "Time": 41584,
    "X": 654,
    "Y": 366,
    "Delta": null,
    "KeyCode": null
  },
  {
    "Type": "MouseMove",
    "Time": 42356,
    "X": 654,
    "Y": 363,
    "Delta": null,
    "KeyCode": null
  },
  {
    "Type": "MouseMove",
    "Time": 42378,
    "X": 660,
    "Y": 360,
    "Delta": null,
    "KeyCode": null
  },
  {
    "Type": "MouseMove",
    "Time": 42400,
    "X": 666,
    "Y": 357,
    "Delta": null,
    "KeyCode": null
  },
  {
    "Type": "MouseMove",
    "Time": 42423,
    "X": 675,
    "Y": 354,
    "Delta": null,
    "KeyCode": null
  },
  {
    "Type": "MouseMove",
    "Time": 42423,
    "X": 678,
    "Y": 354,
    "Delta": null,
    "KeyCode": null
  },
  {
    "Type": "MouseMove",
    "Time": 42452,
    "X": 687,
    "Y": 348,
    "Delta": null,
    "KeyCode": null
  },
  {
    "Type": "MouseMove",
    "Time": 42473,
    "X": 702,
    "Y": 345,
    "Delta": null,
    "KeyCode": null
  },
  {
    "Type": "MouseMove",
    "Time": 42497,
    "X": 708,
    "Y": 342,
    "Delta": null,
    "KeyCode": null
  },
  {
    "Type": "MouseMove",
    "Time": 42518,
    "X": 717,
    "Y": 342,
    "Delta": null,
    "KeyCode": null
  },
  {
    "Type": "MouseMove",
    "Time": 42519,
    "X": 723,
    "Y": 342,
    "Delta": null,
    "KeyCode": null
  },
  {
    "Type": "MouseMove",
    "Time": 42551,
    "X": 744,
    "Y": 336,
    "Delta": null,
    "KeyCode": null
  },
  {
    "Type": "MouseMove",
    "Time": 42573,
    "X": 768,
    "Y": 333,
    "Delta": null,
    "KeyCode": null
  },
  {
    "Type": "MouseMove",
    "Time": 42575,
    "X": 774,
    "Y": 333,
    "Delta": null,
    "KeyCode": null
  },
  {
    "Type": "MouseMove",
    "Time": 42598,
    "X": 783,
    "Y": 333,
    "Delta": null,
    "KeyCode": null
  },
  {
    "Type": "MouseMove",
    "Time": 42621,
    "X": 792,
    "Y": 330,
    "Delta": null,
    "KeyCode": null
  },
  {
    "Type": "MouseMove",
    "Time": 42645,
    "X": 801,
    "Y": 330,
    "Delta": null,
    "KeyCode": null
  },
  {
    "Type": "MouseMove",
    "Time": 42649,
    "X": 804,
    "Y": 330,
    "Delta": null,
    "KeyCode": null
  },
  {
    "Type": "MouseMove",
    "Time": 42673,
    "X": 813,
    "Y": 330,
    "Delta": null,
    "KeyCode": null
  },
  {
    "Type": "MouseMove",
    "Time": 42674,
    "X": 822,
    "Y": 330,
    "Delta": null,
    "KeyCode": null
  },
  {
    "Type": "MouseMove",
    "Time": 42681,
    "X": 825,
    "Y": 330,
    "Delta": null,
    "KeyCode": null
  },
  {
    "Type": "MouseMove",
    "Time": 42703,
    "X": 831,
    "Y": 330,
    "Delta": null,
    "KeyCode": null
  },
  {
    "Type": "MouseMove",
    "Time": 42705,
    "X": 834,
    "Y": 330,
    "Delta": null,
    "KeyCode": null
  },
  {
    "Type": "MouseMove",
    "Time": 42734,
    "X": 837,
    "Y": 330,
    "Delta": null,
    "KeyCode": null
  },
  {
    "Type": "MouseMove",
    "Time": 42765,
    "X": 843,
    "Y": 333,
    "Delta": null,
    "KeyCode": null
  },
  {
    "Type": "MouseMove",
    "Time": 42769,
    "X": 846,
    "Y": 333,
    "Delta": null,
    "KeyCode": null
  },
  {
    "Type": "MouseMove",
    "Time": 42795,
    "X": 852,
    "Y": 333,
    "Delta": null,
    "KeyCode": null
  },
  {
    "Type": "MouseMove",
    "Time": 42833,
    "X": 855,
    "Y": 336,
    "Delta": null,
    "KeyCode": null
  },
  {
    "Type": "MouseMove",
    "Time": 42891,
    "X": 858,
    "Y": 336,
    "Delta": null,
    "KeyCode": null
  },
  {
    "Type": "MouseMove",
    "Time": 42999,
    "X": 864,
    "Y": 339,
    "Delta": null,
    "KeyCode": null
  },
  {
    "Type": "MouseMove",
    "Time": 43055,
    "X": 867,
    "Y": 342,
    "Delta": null,
    "KeyCode": null
  },
  {
    "Type": "MouseMove",
    "Time": 43108,
    "X": 873,
    "Y": 342,
    "Delta": null,
    "KeyCode": null
  },
  {
    "Type": "MouseMove",
    "Time": 43131,
    "X": 876,
    "Y": 345,
    "Delta": null,
    "KeyCode": null
  },
  {
    "Type": "MouseMove",
    "Time": 43181,
    "X": 876,
    "Y": 348,
    "Delta": null,
    "KeyCode": null
  },
  {
    "Type": "MouseMove",
    "Time": 43204,
    "X": 879,
    "Y": 348,
    "Delta": null,
    "KeyCode": null
  },
  {
    "Type": "MouseMove",
    "Time": 43205,
    "X": 879,
    "Y": 351,
    "Delta": null,
    "KeyCode": null
  },
  {
    "Type": "MouseMove",
    "Time": 43213,
    "X": 882,
    "Y": 351,
    "Delta": null,
    "KeyCode": null
  },
  {
    "Type": "MouseMove",
    "Time": 43221,
    "X": 882,
    "Y": 354,
    "Delta": null,
    "KeyCode": null
  },
  {
    "Type": "MouseMove",
    "Time": 43237,
    "X": 885,
    "Y": 354,
    "Delta": null,
    "KeyCode": null
  },
  {
    "Type": "MouseMove",
    "Time": 43377,
    "X": 885,
    "Y": 357,
    "Delta": null,
    "KeyCode": null
  },
  {
    "Type": "MouseMove",
    "Time": 43405,
    "X": 888,
    "Y": 357,
    "Delta": null,
    "KeyCode": null
  },
  {
    "Type": "MouseMove",
    "Time": 43844,
    "X": 888,
    "Y": 360,
    "Delta": null,
    "KeyCode": null
  },
  {
    "Type": "MouseMove",
    "Time": 44272,
    "X": 891,
    "Y": 360,
    "Delta": null,
    "KeyCode": null
  },
  {
    "Type": "DragStart",
    "Time": 45065,
    "X": 891,
    "Y": 360,
    "Delta": null,
    "KeyCode": null
  },
  {
    "Type": "DragEnd",
    "Time": 45178,
    "X": 891,
    "Y": 360,
    "Delta": null,
    "KeyCode": null
  },
  {
    "Type": "MouseMove",
    "Time": 45285,
    "X": 891,
    "Y": 357,
    "Delta": null,
    "KeyCode": null
  },
  {
    "Type": "MouseMove",
    "Time": 45291,
    "X": 894,
    "Y": 354,
    "Delta": null,
    "KeyCode": null
  },
  {
    "Type": "MouseMove",
    "Time": 45315,
    "X": 894,
    "Y": 348,
    "Delta": null,
    "KeyCode": null
  },
  {
    "Type": "MouseMove",
    "Time": 45340,
    "X": 894,
    "Y": 345,
    "Delta": null,
    "KeyCode": null
  },
  {
    "Type": "MouseMove",
    "Time": 45365,
    "X": 894,
    "Y": 342,
    "Delta": null,
    "KeyCode": null
  },
  {
    "Type": "MouseMove",
    "Time": 45417,
    "X": 894,
    "Y": 336,
    "Delta": null,
    "KeyCode": null
  },
  {
    "Type": "MouseMove",
    "Time": 45444,
    "X": 894,
    "Y": 333,
    "Delta": null,
    "KeyCode": null
  },
  {
    "Type": "DragStart",
    "Time": 45518,
    "X": 894,
    "Y": 333,
    "Delta": null,
    "KeyCode": null
  },
  {
    "Type": "MouseMove",
    "Time": 45565,
    "X": 897,
    "Y": 333,
    "Delta": null,
    "KeyCode": null
  },
  {
    "Type": "DragEnd",
    "Time": 45637,
    "X": 897,
    "Y": 333,
    "Delta": null,
    "KeyCode": null
  },
  {
    "Type": "MouseMove",
    "Time": 45667,
    "X": 897,
    "Y": 330,
    "Delta": null,
    "KeyCode": null
  },
  {
    "Type": "MouseMove",
    "Time": 45694,
    "X": 900,
    "Y": 327,
    "Delta": null,
    "KeyCode": null
  },
  {
    "Type": "MouseMove",
    "Time": 45757,
    "X": 903,
    "Y": 327,
    "Delta": null,
    "KeyCode": null
  },
  {
    "Type": "MouseMove",
    "Time": 45765,
    "X": 906,
    "Y": 324,
    "Delta": null,
    "KeyCode": null
  },
  {
    "Type": "MouseMove",
    "Time": 45787,
    "X": 915,
    "Y": 324,
    "Delta": null,
    "KeyCode": null
  },
  {
    "Type": "MouseMove",
    "Time": 45789,
    "X": 918,
    "Y": 324,
    "Delta": null,
    "KeyCode": null
  },
  {
    "Type": "MouseMove",
    "Time": 45817,
    "X": 930,
    "Y": 318,
    "Delta": null,
    "KeyCode": null
  },
  {
    "Type": "MouseMove",
    "Time": 45821,
    "X": 936,
    "Y": 318,
    "Delta": null,
    "KeyCode": null
  },
  {
    "Type": "MouseMove",
    "Time": 45881,
    "X": 939,
    "Y": 318,
    "Delta": null,
    "KeyCode": null
  },
  {
    "Type": "MouseMove",
    "Time": 45924,
    "X": 942,
    "Y": 318,
    "Delta": null,
    "KeyCode": null
  },
  {
    "Type": "MouseMove",
    "Time": 45927,
    "X": 945,
    "Y": 318,
    "Delta": null,
    "KeyCode": null
  },
  {
    "Type": "DragStart",
    "Time": 46012,
    "X": 945,
    "Y": 318,
    "Delta": null,
    "KeyCode": null
  },
  {
    "Type": "MouseMove",
    "Time": 46034,
    "X": 945,
    "Y": 321,
    "Delta": null,
    "KeyCode": null
  },
  {
    "Type": "DragEnd",
    "Time": 46101,
    "X": 945,
    "Y": 321,
    "Delta": null,
    "KeyCode": null
  },
  {
    "Type": "MouseMove",
    "Time": 46192,
    "X": 945,
    "Y": 318,
    "Delta": null,
    "KeyCode": null
  },
  {
    "Type": "MouseMove",
    "Time": 46193,
    "X": 945,
    "Y": 315,
    "Delta": null,
    "KeyCode": null
  },
  {
    "Type": "MouseMove",
    "Time": 46201,
    "X": 945,
    "Y": 309,
    "Delta": null,
    "KeyCode": null
  },
  {
    "Type": "MouseMove",
    "Time": 46224,
    "X": 945,
    "Y": 303,
    "Delta": null,
    "KeyCode": null
  },
  {
    "Type": "MouseMove",
    "Time": 46247,
    "X": 945,
    "Y": 291,
    "Delta": null,
    "KeyCode": null
  },
  {
    "Type": "DragStart",
    "Time": 46472,
    "X": 945,
    "Y": 291,
    "Delta": null,
    "KeyCode": null
  },
  {
    "Type": "DragEnd",
    "Time": 46543,
    "X": 945,
    "Y": 291,
    "Delta": null,
    "KeyCode": null
  },
  {
    "Type": "MouseMove",
    "Time": 46625,
    "X": 939,
    "Y": 288,
    "Delta": null,
    "KeyCode": null
  },
  {
    "Type": "MouseMove",
    "Time": 46627,
    "X": 936,
    "Y": 288,
    "Delta": null,
    "KeyCode": null
  },
  {
    "Type": "MouseMove",
    "Time": 46635,
    "X": 930,
    "Y": 288,
    "Delta": null,
    "KeyCode": null
  },
  {
    "Type": "MouseMove",
    "Time": 46761,
    "X": 924,
    "Y": 288,
    "Delta": null,
    "KeyCode": null
  },
  {
    "Type": "MouseMove",
    "Time": 46885,
    "X": 921,
    "Y": 288,
    "Delta": null,
    "KeyCode": null
  },
  {
    "Type": "MouseMove",
    "Time": 46909,
    "X": 918,
    "Y": 288,
    "Delta": null,
    "KeyCode": null
  },
  {
    "Type": "DragStart",
    "Time": 47089,
    "X": 918,
    "Y": 288,
    "Delta": null,
    "KeyCode": null
  },
  {
    "Type": "DragEnd",
    "Time": 47205,
    "X": 918,
    "Y": 288,
    "Delta": null,
    "KeyCode": null
  },
  {
    "Type": "MouseMove",
    "Time": 47398,
    "X": 924,
    "Y": 294,
    "Delta": null,
    "KeyCode": null
  },
  {
    "Type": "MouseMove",
    "Time": 47421,
    "X": 930,
    "Y": 297,
    "Delta": null,
    "KeyCode": null
  },
  {
    "Type": "MouseMove",
    "Time": 47444,
    "X": 939,
    "Y": 300,
    "Delta": null,
    "KeyCode": null
  },
  {
    "Type": "MouseMove",
    "Time": 47467,
    "X": 957,
    "Y": 306,
    "Delta": null,
    "KeyCode": null
  },
  {
    "Type": "MouseMove",
    "Time": 47490,
    "X": 972,
    "Y": 315,
    "Delta": null,
    "KeyCode": null
  },
  {
    "Type": "MouseMove",
    "Time": 47497,
    "X": 975,
    "Y": 315,
    "Delta": null,
    "KeyCode": null
  },
  {
    "Type": "MouseMove",
    "Time": 47505,
    "X": 978,
    "Y": 318,
    "Delta": null,
    "KeyCode": null
  },
  {
    "Type": "MouseMove",
    "Time": 47521,
    "X": 981,
    "Y": 318,
    "Delta": null,
    "KeyCode": null
  },
  {
    "Type": "MouseMove",
    "Time": 47544,
    "X": 984,
    "Y": 321,
    "Delta": null,
    "KeyCode": null
  },
  {
    "Type": "MouseMove",
    "Time": 47545,
    "X": 987,
    "Y": 324,
    "Delta": null,
    "KeyCode": null
  },
  {
    "Type": "MouseMove",
    "Time": 47573,
    "X": 996,
    "Y": 327,
    "Delta": null,
    "KeyCode": null
  },
  {
    "Type": "MouseMove",
    "Time": 47598,
    "X": 999,
    "Y": 330,
    "Delta": null,
    "KeyCode": null
  },
  {
    "Type": "MouseMove",
    "Time": 47689,
    "X": 1008,
    "Y": 330,
    "Delta": null,
    "KeyCode": null
  },
  {
    "Type": "MouseMove",
    "Time": 47717,
    "X": 1014,
    "Y": 330,
    "Delta": null,
    "KeyCode": null
  },
  {
    "Type": "MouseMove",
    "Time": 47810,
    "X": 1017,
    "Y": 330,
    "Delta": null,
    "KeyCode": null
  },
  {
    "Type": "DragStart",
    "Time": 47833,
    "X": 1017,
    "Y": 330,
    "Delta": null,
    "KeyCode": null
  },
  {
    "Type": "DragEnd",
    "Time": 47891,
    "X": 1017,
    "Y": 330,
    "Delta": null,
    "KeyCode": null
  },
  {
    "Type": "MouseMove",
    "Time": 47939,
    "X": 1017,
    "Y": 327,
    "Delta": null,
    "KeyCode": null
  },
  {
    "Type": "MouseMove",
    "Time": 47985,
    "X": 1017,
    "Y": 321,
    "Delta": null,
    "KeyCode": null
  },
  {
    "Type": "MouseMove",
    "Time": 48009,
    "X": 1014,
    "Y": 309,
    "Delta": null,
    "KeyCode": null
  },
  {
    "Type": "MouseMove",
    "Time": 48034,
    "X": 1017,
    "Y": 300,
    "Delta": null,
    "KeyCode": null
  },
  {
    "Type": "MouseMove",
    "Time": 48080,
    "X": 1017,
    "Y": 297,
    "Delta": null,
    "KeyCode": null
  },
  {
    "Type": "MouseMove",
    "Time": 48104,
    "X": 1020,
    "Y": 294,
    "Delta": null,
    "KeyCode": null
  },
  {
    "Type": "DragStart",
    "Time": 48152,
    "X": 1020,
    "Y": 294,
    "Delta": null,
    "KeyCode": null
  },
  {
    "Type": "DragEnd",
    "Time": 48245,
    "X": 1020,
    "Y": 294,
    "Delta": null,
    "KeyCode": null
  },
  {
    "Type": "MouseMove",
    "Time": 48419,
    "X": 1017,
    "Y": 294,
    "Delta": null,
    "KeyCode": null
  },
  {
    "Type": "MouseMove",
    "Time": 48444,
    "X": 1014,
    "Y": 291,
    "Delta": null,
    "KeyCode": null
  },
  {
    "Type": "MouseMove",
    "Time": 48468,
    "X": 1011,
    "Y": 291,
    "Delta": null,
    "KeyCode": null
  },
  {
    "Type": "MouseMove",
    "Time": 48492,
    "X": 1008,
    "Y": 291,
    "Delta": null,
    "KeyCode": null
  },
  {
    "Type": "MouseMove",
    "Time": 48518,
    "X": 1008,
    "Y": 288,
    "Delta": null,
    "KeyCode": null
  },
  {
    "Type": "MouseMove",
    "Time": 48551,
    "X": 1002,
    "Y": 288,
    "Delta": null,
    "KeyCode": null
  },
  {
    "Type": "MouseMove",
    "Time": 48602,
    "X": 999,
    "Y": 288,
    "Delta": null,
    "KeyCode": null
  },
  {
    "Type": "MouseMove",
    "Time": 48749,
    "X": 999,
    "Y": 291,
    "Delta": null,
    "KeyCode": null
  },
  {
    "Type": "MouseMove",
    "Time": 48755,
    "X": 996,
    "Y": 291,
    "Delta": null,
    "KeyCode": null
  },
  {
    "Type": "DragStart",
    "Time": 48836,
    "X": 996,
    "Y": 291,
    "Delta": null,
    "KeyCode": null
  },
  {
    "Type": "DragEnd",
    "Time": 48933,
    "X": 996,
    "Y": 291,
    "Delta": null,
    "KeyCode": null
  },
  {
    "Type": "MouseMove",
    "Time": 49008,
    "X": 993,
    "Y": 294,
    "Delta": null,
    "KeyCode": null
  },
  {
    "Type": "MouseMove",
    "Time": 49013,
    "X": 993,
    "Y": 297,
    "Delta": null,
    "KeyCode": null
  },
  {
    "Type": "MouseMove",
    "Time": 49039,
    "X": 993,
    "Y": 300,
    "Delta": null,
    "KeyCode": null
  },
  {
    "Type": "MouseMove",
    "Time": 49063,
    "X": 993,
    "Y": 303,
    "Delta": null,
    "KeyCode": null
  },
  {
    "Type": "MouseMove",
    "Time": 49084,
    "X": 993,
    "Y": 309,
    "Delta": null,
    "KeyCode": null
  },
  {
    "Type": "MouseMove",
    "Time": 49106,
    "X": 993,
    "Y": 315,
    "Delta": null,
    "KeyCode": null
  },
  {
    "Type": "MouseMove",
    "Time": 49109,
    "X": 993,
    "Y": 318,
    "Delta": null,
    "KeyCode": null
  },
  {
    "Type": "MouseMove",
    "Time": 49173,
    "X": 990,
    "Y": 321,
    "Delta": null,
    "KeyCode": null
  },
  {
    "Type": "MouseMove",
    "Time": 49218,
    "X": 990,
    "Y": 324,
    "Delta": null,
    "KeyCode": null
  },
  {
    "Type": "DragStart",
    "Time": 49284,
    "X": 990,
    "Y": 324,
    "Delta": null,
    "KeyCode": null
  },
  {
    "Type": "MouseMove",
    "Time": 49305,
    "X": 990,
    "Y": 327,
    "Delta": null,
    "KeyCode": null
  },
  {
    "Type": "DragEnd",
    "Time": 49360,
    "X": 990,
    "Y": 327,
    "Delta": null,
    "KeyCode": null
  },
  {
    "Type": "MouseMove",
    "Time": 49463,
    "X": 990,
    "Y": 330,
    "Delta": null,
    "KeyCode": null
  },
  {
    "Type": "MouseMove",
    "Time": 49491,
    "X": 987,
    "Y": 336,
    "Delta": null,
    "KeyCode": null
  },
  {
    "Type": "MouseMove",
    "Time": 49514,
    "X": 984,
    "Y": 339,
    "Delta": null,
    "KeyCode": null
  },
  {
    "Type": "MouseMove",
    "Time": 49539,
    "X": 984,
    "Y": 342,
    "Delta": null,
    "KeyCode": null
  },
  {
    "Type": "MouseMove",
    "Time": 49543,
    "X": 984,
    "Y": 345,
    "Delta": null,
    "KeyCode": null
  },
  {
    "Type": "MouseMove",
    "Time": 49551,
    "X": 981,
    "Y": 345,
    "Delta": null,
    "KeyCode": null
  },
  {
    "Type": "MouseMove",
    "Time": 49685,
    "X": 981,
    "Y": 348,
    "Delta": null,
    "KeyCode": null
  },
  {
    "Type": "MouseMove",
    "Time": 49689,
    "X": 978,
    "Y": 354,
    "Delta": null,
    "KeyCode": null
  },
  {
    "Type": "MouseMove",
    "Time": 49713,
    "X": 969,
    "Y": 363,
    "Delta": null,
    "KeyCode": null
  },
  {
    "Type": "MouseMove",
    "Time": 49721,
    "X": 966,
    "Y": 366,
    "Delta": null,
    "KeyCode": null
  },
  {
    "Type": "MouseMove",
    "Time": 49743,
    "X": 954,
    "Y": 375,
    "Delta": null,
    "KeyCode": null
  },
  {
    "Type": "MouseMove",
    "Time": 49765,
    "X": 930,
    "Y": 396,
    "Delta": null,
    "KeyCode": null
  },
  {
    "Type": "MouseMove",
    "Time": 49769,
    "X": 921,
    "Y": 402,
    "Delta": null,
    "KeyCode": null
  },
  {
    "Type": "MouseMove",
    "Time": 49791,
    "X": 894,
    "Y": 420,
    "Delta": null,
    "KeyCode": null
  },
  {
    "Type": "MouseMove",
    "Time": 49793,
    "X": 879,
    "Y": 429,
    "Delta": null,
    "KeyCode": null
  },
  {
    "Type": "MouseMove",
    "Time": 49802,
    "X": 873,
    "Y": 432,
    "Delta": null,
    "KeyCode": null
  },
  {
    "Type": "MouseMove",
    "Time": 49826,
    "X": 855,
    "Y": 444,
    "Delta": null,
    "KeyCode": null
  },
  {
    "Type": "MouseMove",
    "Time": 49854,
    "X": 828,
    "Y": 459,
    "Delta": null,
    "KeyCode": null
  },
  {
    "Type": "MouseMove",
    "Time": 49878,
    "X": 813,
    "Y": 471,
    "Delta": null,
    "KeyCode": null
  },
  {
    "Type": "MouseMove",
    "Time": 49903,
    "X": 798,
    "Y": 486,
    "Delta": null,
    "KeyCode": null
  },
  {
    "Type": "MouseMove",
    "Time": 49924,
    "X": 795,
    "Y": 489,
    "Delta": null,
    "KeyCode": null
  },
  {
    "Type": "MouseMove",
    "Time": 49947,
    "X": 795,
    "Y": 498,
    "Delta": null,
    "KeyCode": null
  },
  {
    "Type": "MouseMove",
    "Time": 49948,
    "X": 792,
    "Y": 501,
    "Delta": null,
    "KeyCode": null
  },
  {
    "Type": "MouseMove",
    "Time": 49971,
    "X": 792,
    "Y": 507,
    "Delta": null,
    "KeyCode": null
  },
  {
    "Type": "MouseMove",
    "Time": 49972,
    "X": 792,
    "Y": 513,
    "Delta": null,
    "KeyCode": null
  },
  {
    "Type": "MouseMove",
    "Time": 49995,
    "X": 792,
    "Y": 519,
    "Delta": null,
    "KeyCode": null
  },
  {
    "Type": "MouseMove",
    "Time": 50018,
    "X": 789,
    "Y": 525,
    "Delta": null,
    "KeyCode": null
  },
  {
    "Type": "MouseMove",
    "Time": 50041,
    "X": 789,
    "Y": 531,
    "Delta": null,
    "KeyCode": null
  },
  {
    "Type": "MouseMove",
    "Time": 50064,
    "X": 786,
    "Y": 534,
    "Delta": null,
    "KeyCode": null
  },
  {
    "Type": "MouseMove",
    "Time": 50087,
    "X": 786,
    "Y": 537,
    "Delta": null,
    "KeyCode": null
  },
  {
    "Type": "MouseMove",
    "Time": 50123,
    "X": 786,
    "Y": 540,
    "Delta": null,
    "KeyCode": null
  },
  {
    "Type": "MouseMove",
    "Time": 50155,
    "X": 780,
    "Y": 540,
    "Delta": null,
    "KeyCode": null
  },
  {
    "Type": "MouseMove",
    "Time": 50156,
    "X": 777,
    "Y": 543,
    "Delta": null,
    "KeyCode": null
  },
  {
    "Type": "MouseMove",
    "Time": 50177,
    "X": 762,
    "Y": 543,
    "Delta": null,
    "KeyCode": null
  },
  {
    "Type": "MouseMove",
    "Time": 50179,
    "X": 750,
    "Y": 540,
    "Delta": null,
    "KeyCode": null
  },
  {
    "Type": "MouseMove",
    "Time": 50206,
    "X": 720,
    "Y": 522,
    "Delta": null,
    "KeyCode": null
  },
  {
    "Type": "MouseMove",
    "Time": 50230,
    "X": 702,
    "Y": 498,
    "Delta": null,
    "KeyCode": null
  },
  {
    "Type": "MouseMove",
    "Time": 50252,
    "X": 690,
    "Y": 486,
    "Delta": null,
    "KeyCode": null
  },
  {
    "Type": "MouseMove",
    "Time": 50276,
    "X": 669,
    "Y": 459,
    "Delta": null,
    "KeyCode": null
  },
  {
    "Type": "MouseMove",
    "Time": 50299,
    "X": 648,
    "Y": 429,
    "Delta": null,
    "KeyCode": null
  },
  {
    "Type": "MouseMove",
    "Time": 50301,
    "X": 642,
    "Y": 420,
    "Delta": null,
    "KeyCode": null
  },
  {
    "Type": "MouseMove",
    "Time": 50329,
    "X": 630,
    "Y": 402,
    "Delta": null,
    "KeyCode": null
  },
  {
    "Type": "MouseMove",
    "Time": 50333,
    "X": 627,
    "Y": 399,
    "Delta": null,
    "KeyCode": null
  },
  {
    "Type": "MouseMove",
    "Time": 50363,
    "X": 624,
    "Y": 390,
    "Delta": null,
    "KeyCode": null
  },
  {
    "Type": "MouseMove",
    "Time": 50385,
    "X": 624,
    "Y": 372,
    "Delta": null,
    "KeyCode": null
  },
  {
    "Type": "MouseMove",
    "Time": 50412,
    "X": 627,
    "Y": 360,
    "Delta": null,
    "KeyCode": null
  },
  {
    "Type": "MouseMove",
    "Time": 50511,
    "X": 630,
    "Y": 360,
    "Delta": null,
    "KeyCode": null
  },
  {
    "Type": "MouseMove",
    "Time": 50536,
    "X": 633,
    "Y": 357,
    "Delta": null,
    "KeyCode": null
  },
  {
    "Type": "MouseMove",
    "Time": 50558,
    "X": 639,
    "Y": 357,
    "Delta": null,
    "KeyCode": null
  },
  {
    "Type": "MouseMove",
    "Time": 50581,
    "X": 642,
    "Y": 354,
    "Delta": null,
    "KeyCode": null
  },
  {
    "Type": "MouseMove",
    "Time": 50583,
    "X": 645,
    "Y": 354,
    "Delta": null,
    "KeyCode": null
  },
  {
    "Type": "MouseMove",
    "Time": 50616,
    "X": 651,
    "Y": 354,
    "Delta": null,
    "KeyCode": null
  },
  {
    "Type": "MouseMove",
    "Time": 50631,
    "X": 654,
    "Y": 354,
    "Delta": null,
    "KeyCode": null
  },
  {
    "Type": "MouseMove",
    "Time": 50687,
    "X": 657,
    "Y": 354,
    "Delta": null,
    "KeyCode": null
  },
  {
    "Type": "DragStart",
    "Time": 50762,
    "X": 657,
    "Y": 354,
    "Delta": null,
    "KeyCode": null
  },
  {
    "Type": "DragEnd",
    "Time": 50803,
    "X": 657,
    "Y": 354,
    "Delta": null,
    "KeyCode": null
  },
  {
    "Type": "MouseMove",
    "Time": 50960,
    "X": 651,
    "Y": 360,
    "Delta": null,
    "KeyCode": null
  },
  {
    "Type": "MouseMove",
    "Time": 50984,
    "X": 648,
    "Y": 369,
    "Delta": null,
    "KeyCode": null
  },
  {
    "Type": "MouseMove",
    "Time": 51008,
    "X": 642,
    "Y": 378,
    "Delta": null,
    "KeyCode": null
  },
  {
    "Type": "MouseMove",
    "Time": 51013,
    "X": 639,
    "Y": 384,
    "Delta": null,
    "KeyCode": null
  },
  {
    "Type": "MouseMove",
    "Time": 51021,
    "X": 636,
    "Y": 390,
    "Delta": null,
    "KeyCode": null
  },
  {
    "Type": "MouseMove",
    "Time": 51029,
    "X": 633,
    "Y": 393,
    "Delta": null,
    "KeyCode": null
  },
  {
    "Type": "MouseMove",
    "Time": 51054,
    "X": 630,
    "Y": 402,
    "Delta": null,
    "KeyCode": null
  },
  {
    "Type": "MouseMove",
    "Time": 51063,
    "X": 627,
    "Y": 405,
    "Delta": null,
    "KeyCode": null
  },
  {
    "Type": "MouseMove",
    "Time": 51085,
    "X": 627,
    "Y": 408,
    "Delta": null,
    "KeyCode": null
  },
  {
    "Type": "MouseMove",
    "Time": 51107,
    "X": 624,
    "Y": 414,
    "Delta": null,
    "KeyCode": null
  },
  {
    "Type": "MouseMove",
    "Time": 51119,
    "X": 624,
    "Y": 417,
    "Delta": null,
    "KeyCode": null
  },
  {
    "Type": "MouseMove",
    "Time": 51135,
    "X": 624,
    "Y": 420,
    "Delta": null,
    "KeyCode": null
  },
  {
    "Type": "MouseMove",
    "Time": 51163,
    "X": 621,
    "Y": 426,
    "Delta": null,
    "KeyCode": null
  },
  {
    "Type": "MouseMove",
    "Time": 51185,
    "X": 615,
    "Y": 432,
    "Delta": null,
    "KeyCode": null
  },
  {
    "Type": "MouseMove",
    "Time": 51191,
    "X": 615,
    "Y": 438,
    "Delta": null,
    "KeyCode": null
  },
  {
    "Type": "MouseMove",
    "Time": 51199,
    "X": 612,
    "Y": 441,
    "Delta": null,
    "KeyCode": null
  },
  {
    "Type": "MouseMove",
    "Time": 51224,
    "X": 606,
    "Y": 450,
    "Delta": null,
    "KeyCode": null
  },
  {
    "Type": "MouseMove",
    "Time": 51231,
    "X": 606,
    "Y": 453,
    "Delta": null,
    "KeyCode": null
  },
  {
    "Type": "MouseMove",
    "Time": 51258,
    "X": 594,
    "Y": 465,
    "Delta": null,
    "KeyCode": null
  },
  {
    "Type": "MouseMove",
    "Time": 51281,
    "X": 591,
    "Y": 471,
    "Delta": null,
    "KeyCode": null
  },
  {
    "Type": "MouseMove",
    "Time": 51321,
    "X": 588,
    "Y": 474,
    "Delta": null,
    "KeyCode": null
  },
  {
    "Type": "MouseMove",
    "Time": 51343,
    "X": 582,
    "Y": 477,
    "Delta": null,
    "KeyCode": null
  },
  {
    "Type": "MouseMove",
    "Time": 51366,
    "X": 576,
    "Y": 480,
    "Delta": null,
    "KeyCode": null
  },
  {
    "Type": "MouseMove",
    "Time": 51388,
    "X": 570,
    "Y": 486,
    "Delta": null,
    "KeyCode": null
  },
  {
    "Type": "MouseMove",
    "Time": 51412,
    "X": 561,
    "Y": 489,
    "Delta": null,
    "KeyCode": null
  },
  {
    "Type": "MouseMove",
    "Time": 51433,
    "X": 546,
    "Y": 495,
    "Delta": null,
    "KeyCode": null
  },
  {
    "Type": "MouseMove",
    "Time": 51455,
    "X": 534,
    "Y": 498,
    "Delta": null,
    "KeyCode": null
  },
  {
    "Type": "MouseMove",
    "Time": 51479,
    "X": 516,
    "Y": 498,
    "Delta": null,
    "KeyCode": null
  },
  {
    "Type": "MouseMove",
    "Time": 51500,
    "X": 507,
    "Y": 498,
    "Delta": null,
    "KeyCode": null
  },
  {
    "Type": "MouseMove",
    "Time": 51505,
    "X": 504,
    "Y": 498,
    "Delta": null,
    "KeyCode": null
  },
  {
    "Type": "MouseMove",
    "Time": 51617,
    "X": 501,
    "Y": 498,
    "Delta": null,
    "KeyCode": null
  },
  {
    "Type": "MouseMove",
    "Time": 51639,
    "X": 501,
    "Y": 495,
    "Delta": null,
    "KeyCode": null
  },
  {
    "Type": "MouseMove",
    "Time": 51660,
    "X": 501,
    "Y": 492,
    "Delta": null,
    "KeyCode": null
  },
  {
    "Type": "MouseMove",
    "Time": 51683,
    "X": 501,
    "Y": 489,
    "Delta": null,
    "KeyCode": null
  },
  {
    "Type": "MouseMove",
    "Time": 51718,
    "X": 504,
    "Y": 489,
    "Delta": null,
    "KeyCode": null
  },
  {
    "Type": "MouseMove",
    "Time": 51719,
    "X": 504,
    "Y": 486,
    "Delta": null,
    "KeyCode": null
  },
  {
    "Type": "MouseMove",
    "Time": 53205,
    "X": 507,
    "Y": 486,
    "Delta": null,
    "KeyCode": null
  },
  {
    "Type": "MouseMove",
    "Time": 53361,
    "X": 510,
    "Y": 483,
    "Delta": null,
    "KeyCode": null
  },
  {
    "Type": "MouseMove",
    "Time": 53871,
    "X": 513,
    "Y": 483,
    "Delta": null,
    "KeyCode": null
  },
  {
    "Type": "DragStart",
    "Time": 53972,
    "X": 513,
    "Y": 483,
    "Delta": null,
    "KeyCode": null
  },
  {
    "Type": "DragEnd",
    "Time": 54047,
    "X": 513,
    "Y": 483,
    "Delta": null,
    "KeyCode": null
  },
  {
    "Type": "MouseMove",
    "Time": 54298,
    "X": 519,
    "Y": 480,
    "Delta": null,
    "KeyCode": null
  },
  {
    "Type": "MouseMove",
    "Time": 54298,
    "X": 522,
    "Y": 477,
    "Delta": null,
    "KeyCode": null
  },
  {
    "Type": "MouseMove",
    "Time": 54322,
    "X": 531,
    "Y": 474,
    "Delta": null,
    "KeyCode": null
  },
  {
    "Type": "MouseMove",
    "Time": 54347,
    "X": 543,
    "Y": 471,
    "Delta": null,
    "KeyCode": null
  },
  {
    "Type": "MouseMove",
    "Time": 54353,
    "X": 546,
    "Y": 468,
    "Delta": null,
    "KeyCode": null
  },
  {
    "Type": "MouseMove",
    "Time": 54384,
    "X": 558,
    "Y": 468,
    "Delta": null,
    "KeyCode": null
  },
  {
    "Type": "MouseMove",
    "Time": 54385,
    "X": 570,
    "Y": 465,
    "Delta": null,
    "KeyCode": null
  },
  {
    "Type": "MouseMove",
    "Time": 54415,
    "X": 594,
    "Y": 459,
    "Delta": null,
    "KeyCode": null
  },
  {
    "Type": "MouseMove",
    "Time": 54438,
    "X": 630,
    "Y": 450,
    "Delta": null,
    "KeyCode": null
  },
  {
    "Type": "MouseMove",
    "Time": 54441,
    "X": 642,
    "Y": 444,
    "Delta": null,
    "KeyCode": null
  },
  {
    "Type": "MouseMove",
    "Time": 54449,
    "X": 654,
    "Y": 444,
    "Delta": null,
    "KeyCode": null
  },
  {
    "Type": "MouseMove",
    "Time": 54458,
    "X": 666,
    "Y": 441,
    "Delta": null,
    "KeyCode": null
  },
  {
    "Type": "MouseMove",
    "Time": 54466,
    "X": 675,
    "Y": 438,
    "Delta": null,
    "KeyCode": null
  },
  {
    "Type": "MouseMove",
    "Time": 54493,
    "X": 711,
    "Y": 429,
    "Delta": null,
    "KeyCode": null
  },
  {
    "Type": "MouseMove",
    "Time": 54518,
    "X": 744,
    "Y": 420,
    "Delta": null,
    "KeyCode": null
  },
  {
    "Type": "MouseMove",
    "Time": 54521,
    "X": 753,
    "Y": 414,
    "Delta": null,
    "KeyCode": null
  },
  {
    "Type": "MouseMove",
    "Time": 54530,
    "X": 765,
    "Y": 411,
    "Delta": null,
    "KeyCode": null
  },
  {
    "Type": "MouseMove",
    "Time": 54557,
    "X": 798,
    "Y": 396,
    "Delta": null,
    "KeyCode": null
  },
  {
    "Type": "MouseMove",
    "Time": 54584,
    "X": 822,
    "Y": 387,
    "Delta": null,
    "KeyCode": null
  },
  {
    "Type": "MouseMove",
    "Time": 54608,
    "X": 834,
    "Y": 378,
    "Delta": null,
    "KeyCode": null
  },
  {
    "Type": "MouseMove",
    "Time": 54611,
    "X": 837,
    "Y": 378,
    "Delta": null,
    "KeyCode": null
  },
  {
    "Type": "MouseMove",
    "Time": 54619,
    "X": 840,
    "Y": 375,
    "Delta": null,
    "KeyCode": null
  },
  {
    "Type": "MouseMove",
    "Time": 54627,
    "X": 843,
    "Y": 372,
    "Delta": null,
    "KeyCode": null
  },
  {
    "Type": "MouseMove",
    "Time": 54635,
    "X": 849,
    "Y": 369,
    "Delta": null,
    "KeyCode": null
  },
  {
    "Type": "MouseMove",
    "Time": 54643,
    "X": 855,
    "Y": 363,
    "Delta": null,
    "KeyCode": null
  },
  {
    "Type": "MouseMove",
    "Time": 54672,
    "X": 870,
    "Y": 351,
    "Delta": null,
    "KeyCode": null
  },
  {
    "Type": "MouseMove",
    "Time": 54698,
    "X": 882,
    "Y": 339,
    "Delta": null,
    "KeyCode": null
  },
  {
    "Type": "MouseMove",
    "Time": 54727,
    "X": 885,
    "Y": 336,
    "Delta": null,
    "KeyCode": null
  },
  {
    "Type": "MouseMove",
    "Time": 54753,
    "X": 888,
    "Y": 333,
    "Delta": null,
    "KeyCode": null
  },
  {
    "Type": "MouseMove",
    "Time": 54783,
    "X": 894,
    "Y": 324,
    "Delta": null,
    "KeyCode": null
  },
  {
    "Type": "MouseMove",
    "Time": 54809,
    "X": 900,
    "Y": 318,
    "Delta": null,
    "KeyCode": null
  },
  {
    "Type": "MouseMove",
    "Time": 54835,
    "X": 900,
    "Y": 315,
    "Delta": null,
    "KeyCode": null
  },
  {
    "Type": "MouseMove",
    "Time": 54888,
    "X": 903,
    "Y": 312,
    "Delta": null,
    "KeyCode": null
  },
  {
    "Type": "MouseMove",
    "Time": 54915,
    "X": 903,
    "Y": 306,
    "Delta": null,
    "KeyCode": null
  },
  {
    "Type": "MouseMove",
    "Time": 54967,
    "X": 903,
    "Y": 303,
    "Delta": null,
    "KeyCode": null
  },
  {
    "Type": "MouseMove",
    "Time": 55045,
    "X": 903,
    "Y": 300,
    "Delta": null,
    "KeyCode": null
  },
  {
    "Type": "MouseMove",
    "Time": 55070,
    "X": 903,
    "Y": 297,
    "Delta": null,
    "KeyCode": null
  },
  {
    "Type": "MouseMove",
    "Time": 55100,
    "X": 900,
    "Y": 294,
    "Delta": null,
    "KeyCode": null
  },
  {
    "Type": "DragStart",
    "Time": 57074,
    "X": 900,
    "Y": 294,
    "Delta": null,
    "KeyCode": null
  },
  {
    "Type": "DragEnd",
    "Time": 57120,
    "X": 900,
    "Y": 294,
    "Delta": null,
    "KeyCode": null
  },
  {
    "Type": "MouseMove",
    "Time": 57197,
    "X": 903,
    "Y": 294,
    "Delta": null,
    "KeyCode": null
  },
  {
    "Type": "MouseMove",
    "Time": 57205,
    "X": 903,
    "Y": 291,
    "Delta": null,
    "KeyCode": null
  },
  {
    "Type": "MouseMove",
    "Time": 57213,
    "X": 906,
    "Y": 291,
    "Delta": null,
    "KeyCode": null
  },
  {
    "Type": "MouseMove",
    "Time": 57221,
    "X": 909,
    "Y": 291,
    "Delta": null,
    "KeyCode": null
  },
  {
    "Type": "MouseMove",
    "Time": 57246,
    "X": 912,
    "Y": 288,
    "Delta": null,
    "KeyCode": null
  },
  {
    "Type": "MouseMove",
    "Time": 57270,
    "X": 918,
    "Y": 288,
    "Delta": null,
    "KeyCode": null
  },
  {
    "Type": "MouseMove",
    "Time": 57314,
    "X": 921,
    "Y": 288,
    "Delta": null,
    "KeyCode": null
  },
  {
    "Type": "MouseMove",
    "Time": 57365,
    "X": 924,
    "Y": 288,
    "Delta": null,
    "KeyCode": null
  },
  {
    "Type": "MouseMove",
    "Time": 57366,
    "X": 927,
    "Y": 288,
    "Delta": null,
    "KeyCode": null
  },
  {
    "Type": "MouseMove",
    "Time": 57387,
    "X": 930,
    "Y": 288,
    "Delta": null,
    "KeyCode": null
  },
  {
    "Type": "MouseMove",
    "Time": 57613,
    "X": 933,
    "Y": 291,
    "Delta": null,
    "KeyCode": null
  },
  {
    "Type": "MouseMove",
    "Time": 57635,
    "X": 933,
    "Y": 294,
    "Delta": null,
    "KeyCode": null
  },
  {
    "Type": "MouseMove",
    "Time": 57656,
    "X": 936,
    "Y": 297,
    "Delta": null,
    "KeyCode": null
  },
  {
    "Type": "MouseMove",
    "Time": 57823,
    "X": 939,
    "Y": 297,
    "Delta": null,
    "KeyCode": null
  },
  {
    "Type": "DragStart",
    "Time": 57898,
    "X": 939,
    "Y": 297,
    "Delta": null,
    "KeyCode": null
  },
  {
    "Type": "DragEnd",
    "Time": 57978,
    "X": 939,
    "Y": 297,
    "Delta": null,
    "KeyCode": null
  },
  {
    "Type": "MouseMove",
    "Time": 58463,
    "X": 939,
    "Y": 300,
    "Delta": null,
    "KeyCode": null
  },
  {
    "Type": "MouseMove",
    "Time": 58486,
    "X": 936,
    "Y": 306,
    "Delta": null,
    "KeyCode": null
  },
  {
    "Type": "MouseMove",
    "Time": 58493,
    "X": 933,
    "Y": 306,
    "Delta": null,
    "KeyCode": null
  },
  {
    "Type": "MouseMove",
    "Time": 58526,
    "X": 924,
    "Y": 312,
    "Delta": null,
    "KeyCode": null
  },
  {
    "Type": "MouseMove",
    "Time": 58618,
    "X": 918,
    "Y": 324,
    "Delta": null,
    "KeyCode": null
  },
  {
    "Type": "MouseMove",
    "Time": 58641,
    "X": 906,
    "Y": 342,
    "Delta": null,
    "KeyCode": null
  },
  {
    "Type": "MouseMove",
    "Time": 58647,
    "X": 903,
    "Y": 345,
    "Delta": null,
    "KeyCode": null
  },
  {
    "Type": "MouseMove",
    "Time": 58655,
    "X": 900,
    "Y": 354,
    "Delta": null,
    "KeyCode": null
  },
  {
    "Type": "MouseMove",
    "Time": 58663,
    "X": 894,
    "Y": 360,
    "Delta": null,
    "KeyCode": null
  },
  {
    "Type": "MouseMove",
    "Time": 58671,
    "X": 891,
    "Y": 369,
    "Delta": null,
    "KeyCode": null
  },
  {
    "Type": "MouseMove",
    "Time": 58698,
    "X": 876,
    "Y": 393,
    "Delta": null,
    "KeyCode": null
  },
  {
    "Type": "MouseMove",
    "Time": 58724,
    "X": 855,
    "Y": 420,
    "Delta": null,
    "KeyCode": null
  },
  {
    "Type": "MouseMove",
    "Time": 58746,
    "X": 831,
    "Y": 444,
    "Delta": null,
    "KeyCode": null
  },
  {
    "Type": "MouseMove",
    "Time": 58776,
    "X": 810,
    "Y": 465,
    "Delta": null,
    "KeyCode": null
  },
  {
    "Type": "MouseMove",
    "Time": 58805,
    "X": 798,
    "Y": 480,
    "Delta": null,
    "KeyCode": null
  },
  {
    "Type": "MouseMove",
    "Time": 58807,
    "X": 792,
    "Y": 486,
    "Delta": null,
    "KeyCode": null
  },
  {
    "Type": "MouseMove",
    "Time": 58836,
    "X": 783,
    "Y": 498,
    "Delta": null,
    "KeyCode": null
  },
  {
    "Type": "MouseMove",
    "Time": 58839,
    "X": 780,
    "Y": 501,
    "Delta": null,
    "KeyCode": null
  },
  {
    "Type": "MouseMove",
    "Time": 58869,
    "X": 768,
    "Y": 516,
    "Delta": null,
    "KeyCode": null
  },
  {
    "Type": "MouseMove",
    "Time": 58871,
    "X": 762,
    "Y": 525,
    "Delta": null,
    "KeyCode": null
  },
  {
    "Type": "MouseMove",
    "Time": 58899,
    "X": 756,
    "Y": 543,
    "Delta": null,
    "KeyCode": null
  },
  {
    "Type": "MouseMove",
    "Time": 58903,
    "X": 756,
    "Y": 549,
    "Delta": null,
    "KeyCode": null
  },
  {
    "Type": "MouseMove",
    "Time": 58929,
    "X": 756,
    "Y": 555,
    "Delta": null,
    "KeyCode": null
  },
  {
    "Type": "MouseMove",
    "Time": 58929,
    "X": 756,
    "Y": 558,
    "Delta": null,
    "KeyCode": null
  },
  {
    "Type": "MouseMove",
    "Time": 58962,
    "X": 756,
    "Y": 561,
    "Delta": null,
    "KeyCode": null
  },
  {
    "Type": "MouseMove",
    "Time": 58988,
    "X": 756,
    "Y": 570,
    "Delta": null,
    "KeyCode": null
  },
  {
    "Type": "MouseMove",
    "Time": 58993,
    "X": 753,
    "Y": 576,
    "Delta": null,
    "KeyCode": null
  },
  {
    "Type": "MouseMove",
    "Time": 59020,
    "X": 753,
    "Y": 585,
    "Delta": null,
    "KeyCode": null
  },
  {
    "Type": "MouseMove",
    "Time": 59025,
    "X": 753,
    "Y": 588,
    "Delta": null,
    "KeyCode": null
  },
  {
    "Type": "MouseMove",
    "Time": 59052,
    "X": 753,
    "Y": 594,
    "Delta": null,
    "KeyCode": null
  },
  {
    "Type": "MouseMove",
    "Time": 59083,
    "X": 753,
    "Y": 600,
    "Delta": null,
    "KeyCode": null
  },
  {
    "Type": "MouseMove",
    "Time": 59089,
    "X": 750,
    "Y": 600,
    "Delta": null,
    "KeyCode": null
  },
  {
    "Type": "MouseMove",
    "Time": 59115,
    "X": 750,
    "Y": 606,
    "Delta": null,
    "KeyCode": null
  },
  {
    "Type": "MouseMove",
    "Time": 59140,
    "X": 750,
    "Y": 609,
    "Delta": null,
    "KeyCode": null
  },
  {
    "Type": "MouseMove",
    "Time": 59163,
    "X": 750,
    "Y": 612,
    "Delta": null,
    "KeyCode": null
  },
  {
    "Type": "MouseMove",
    "Time": 59220,
    "X": 750,
    "Y": 615,
    "Delta": null,
    "KeyCode": null
  }
]